Workbook

Sheet Control
A1: Lithium demand in India, 2025-2040: scenario model
A3: Adoption scenario | B3: Base | C3: Low = slow EVs and storage; Base = current trends; High = NITI Aayog-style ambition
A5: Lever: recycling push | B5: =FALSE() -> FALSE | C5: Collection 90% (EV/BESS) and 70% (electronics) by 2030; Li recovery 95%
A6: Lever: overseas assets | B6: =FALSE() -> FALSE | C6: Extra 10 / 30 / 50 kt LCE equity supply in 2030 / 2035 / 2040 (from 2031)
A7: Lever: sodium-ion push | B7: =FALSE() -> FALSE | C7: Sodium-ion share in 2W, 3W and storage +15 / +30 / +40 points by 2030 / 2035 / 2040
A8: Lever: exploration fast-track | B8: =FALSE() -> FALSE | C8: Domestic mining from 2032: 1.5 kt LCE by 2035, 4 kt by 2040
A10: India's accessible share of world lithium supply | B10: 0.03 | C10: Stress test. India is ~1% of world lithium use today and ~3.5% of world GDP

Sheet Results
A1: =" Results: "&Control!B3&" scenario"&IF(OR(Control!B5,Control!B6,Control!B7,Control!B8),", levers on","") -> Results: Base scenario
A2: All quantities in tonnes of lithium carbonate equivalent (t LCE)
A3: Year | B3: EVs | C3: Grid storage | D3: Electronics | E3: Defence and aerospace | F3: Industry | G3: Total demand | H3: Energy transition | I3: Non-energy | J3: Recycling | K3: Domestic mining | L3: Overseas equity | M3: Import ceiling | N3: Available supply | O3: Shortfall | P3: Energy coverage | Q3: Import dependence | R3: Recycled content | S3: Mandate
A4: 2025 | B4: =Calc!P8+Calc!P13+Calc!P18+Calc!P23+Calc!P28+Calc!P33 -> 8774.9049 | C4: =Calc!P39 -> 1331.622 | D4: =Calc!P43+Calc!P46+Calc!P49+Calc!P52+Calc!P55+Calc!P58 -> 4239.8945 | E4: =Calc!P60 -> 150 | F4: =Calc!P61+Calc!P62+Calc!P63 -> 1704 | G4: =Calc!P67 -> 16200.421 | H4: =Calc!P65 -> 10106.527 | I4: =Calc!P66 -> 6093.8945 | J4: =Calc!P73 -> 433.088 | K4: =Calc!P74 -> 0 | L4: =Calc!P75 -> 0 | M4: =Calc!P76 -> 46320 | N4: =Calc!P80 -> 46753.088 | O4: =Calc!P81 -> 0 | P4: =Calc!P82 -> 1 | Q4: =Calc!P83 -> 0.97326687 | R4: =Calc!P84 -> 0.030187877 | S4: =Calc!P85 -> 0
A5: 2026 | B5: =Calc!Q8+Calc!Q13+Calc!Q18+Calc!Q23+Calc!Q28+Calc!Q33 -> 13714.925 | C5: =Calc!Q39 -> 4469.5833 | D5: =Calc!Q43+Calc!Q46+Calc!Q49+Calc!Q52+Calc!Q55+Calc!Q58 -> 4454.7199 | E5: =Calc!Q60 -> 164.07984 | F5: =Calc!Q61+Calc!Q62+Calc!Q63 -> 1798.1568 | G5: =Calc!Q67 -> 24601.465 | H5: =Calc!Q65 -> 18184.509 | I5: =Calc!Q66 -> 6416.9565 | J5: =Calc!Q73 -> 582.80352 | K5: =Calc!Q74 -> 0 | L5: =Calc!Q75 -> 0 | M5: =Calc!Q76 -> 52656 | N5: =Calc!Q80 -> 53238.804 | O5: =Calc!Q81 -> 0 | P5: =Calc!Q82 -> 1 | Q5: =Calc!Q83 -> 0.97631021 | R5: =Calc!Q84 -> 0.025743082 | S5: =Calc!Q85 -> 0
A6: 2027 | B6: =Calc!R8+Calc!R13+Calc!R18+Calc!R23+Calc!R28+Calc!R33 -> 19277.175 | C6: =Calc!R39 -> 7569.5653 | D6: =Calc!R43+Calc!R46+Calc!R49+Calc!R52+Calc!R55+Calc!R58 -> 4674.0342 | E6: =Calc!R60 -> 178.15968 | F6: =Calc!R61+Calc!R62+Calc!R63 -> 1892.3135 | G6: =Calc!R67 -> 33591.248 | H6: =Calc!R65 -> 26846.741 | I6: =Calc!R66 -> 6744.5074 | J6: =Calc!R73 -> 840.78888 | K6: =Calc!R74 -> 0 | L6: =Calc!R75 -> 0 | M6: =Calc!R76 -> 58992 | N6: =Calc!R80 -> 59832.789 | O6: =Calc!R81 -> 0 | P6: =Calc!R82 -> 1 | Q6: =Calc!R83 -> 0.97497 | R6: =Calc!R84 -> 0.026674118 | S6: =Calc!R85 -> 0.05
A7: 2028 | B7: =Calc!S8+Calc!S13+Calc!S18+Calc!S23+Calc!S28+Calc!S33 -> 25485.14 | C7: =Calc!S39 -> 10631.568 | D7: =Calc!S43+Calc!S46+Calc!S49+Calc!S52+Calc!S55+Calc!S58 -> 4897.8374 | E7: =Calc!S60 -> 192.23953 | F7: =Calc!S61+Calc!S62+Calc!S63 -> 1986.4703 | G7: =Calc!S67 -> 43193.256 | H7: =Calc!S65 -> 36116.708 | I7: =Calc!S66 -> 7076.5472 | J7: =Calc!S73 -> 1391.5895 | K7: =Calc!S74 -> 0 | L7: =Calc!S75 -> 0 | M7: =Calc!S76 -> 65328 | N7: =Calc!S80 -> 66719.589 | O7: =Calc!S81 -> 0 | P7: =Calc!S82 -> 1 | Q7: =Calc!S83 -> 0.96778225 | R7: =Calc!S84 -> 0.03392917 | S7: =Calc!S85 -> 0.1
A8: 2029 | B8: =Calc!T8+Calc!T13+Calc!T18+Calc!T23+Calc!T28+Calc!T33 -> 32361.693 | C8: =Calc!T39 -> 13655.591 | D8: =Calc!T43+Calc!T46+Calc!T49+Calc!T52+Calc!T55+Calc!T58 -> 5126.1297 | E8: =Calc!T60 -> 206.31937 | F8: =Calc!T61+Calc!T62+Calc!T63 -> 2080.627 | G8: =Calc!T67 -> 53430.361 | H8: =Calc!T65 -> 46017.285 | I8: =Calc!T66 -> 7413.0761 | J8: =Calc!T73 -> 2025.1009 | K8: =Calc!T74 -> 0 | L8: =Calc!T75 -> 0 | M8: =Calc!T76 -> 71664 | N8: =Calc!T80 -> 73689.101 | O8: =Calc!T81 -> 0 | P8: =Calc!T82 -> 1 | Q8: =Calc!T83 -> 0.96209831 | R8: =Calc!T84 -> 0.039596513 | S8: =Calc!T85 -> 0.15
A9: 2030 | B9: =Calc!U8+Calc!U13+Calc!U18+Calc!U23+Calc!U28+Calc!U33 -> 39929.097 | C9: =Calc!U39 -> 16641.636 | D9: =Calc!U43+Calc!U46+Calc!U49+Calc!U52+Calc!U55+Calc!U58 -> 5358.911 | E9: =Calc!U60 -> 220.39921 | F9: =Calc!U61+Calc!U62+Calc!U63 -> 2174.7838 | G9: =Calc!U67 -> 64324.826 | H9: =Calc!U65 -> 56570.732 | I9: =Calc!U66 -> 7754.094 | J9: =Calc!U73 -> 2987.4018 | K9: =Calc!U74 -> 0 | L9: =Calc!U75 -> 0 | M9: =Calc!U76 -> 78000 | N9: =Calc!U80 -> 80987.402 | O9: =Calc!U81 -> 0 | P9: =Calc!U82 -> 1 | Q9: =Calc!U83 -> 0.95355756 | R9: =Calc!U84 -> 0.048238641 | S9: =Calc!U85 -> 0.2
A10: 2031 | B10: =Calc!V8+Calc!V13+Calc!V18+Calc!V23+Calc!V28+Calc!V33 -> 50908.666 | C10: =Calc!V39 -> 17187.345 | D10: =Calc!V43+Calc!V46+Calc!V49+Calc!V52+Calc!V55+Calc!V58 -> 5653.5939 | E10: =Calc!V60 -> 241.08712 | F10: =Calc!V61+Calc!V62+Calc!V63 -> 2294.9543 | G10: =Calc!V67 -> 76285.647 | H10: =Calc!V65 -> 68096.011 | I10: =Calc!V66 -> 8189.6353 | J10: =Calc!V73 -> 4378.5126 | K10: =Calc!V74 -> 0 | L10: =Calc!V75 -> 0 | M10: =Calc!V76 -> 82800 | N10: =Calc!V80 -> 87178.513 | O10: =Calc!V81 -> 0 | P10: =Calc!V82 -> 1 | Q10: =Calc!V83 -> 0.94260372 | R10: =Calc!V84 -> 0.05936998 | S10: =Calc!V85 -> 0.2
A11: 2032 | B11: =Calc!W8+Calc!W13+Calc!W18+Calc!W23+Calc!W28+Calc!W33 -> 63073.137 | C11: =Calc!W39 -> 17718.112 | D11: =Calc!W43+Calc!W46+Calc!W49+Calc!W52+Calc!W55+Calc!W58 -> 5955.2024 | E11: =Calc!W60 -> 261.77503 | F11: =Calc!W61+Calc!W62+Calc!W63 -> 2415.1248 | G11: =Calc!W67 -> 89423.351 | H11: =Calc!W65 -> 80791.249 | I11: =Calc!W66 -> 8632.1023 | J11: =Calc!W73 -> 6498.4752 | K11: =Calc!W74 -> 0 | L11: =Calc!W75 -> 2400 | M11: =Calc!W76 -> 87600 | N11: =Calc!W80 -> 96498.475 | O11: =Calc!W81 -> 0 | P11: =Calc!W82 -> 1 | Q11: =Calc!W83 -> 0.9273291 | R11: =Calc!W84 -> 0.074913442 | S11: =Calc!W85 -> 0.2
A12: 2033 | B12: =Calc!X8+Calc!X13+Calc!X18+Calc!X23+Calc!X28+Calc!X33 -> 76464.364 | C12: =Calc!X39 -> 18248.323 | D12: =Calc!X43+Calc!X46+Calc!X49+Calc!X52+Calc!X55+Calc!X58 -> 6263.7365 | E12: =Calc!X60 -> 282.46293 | F12: =Calc!X61+Calc!X62+Calc!X63 -> 2535.2954 | G12: =Calc!X67 -> 103794.18 | H12: =Calc!X65 -> 94712.687 | I12: =Calc!X66 -> 9081.4948 | J12: =Calc!X73 -> 9387.9811 | K12: =Calc!X74 -> 0 | L12: =Calc!X75 -> 3600 | M12: =Calc!X76 -> 92400 | N12: =Calc!X80 -> 105387.98 | O12: =Calc!X81 -> 0 | P12: =Calc!X82 -> 1 | Q12: =Calc!X83 -> 0.90955195 | R12: =Calc!X84 -> 0.092972011 | S12: =Calc!X85 -> 0.2
A13: 2034 | B13: =Calc!Y8+Calc!Y13+Calc!Y18+Calc!Y23+Calc!Y28+Calc!Y33 -> 91123.526 | C13: =Calc!Y39 -> 18772.775 | D13: =Calc!Y43+Calc!Y46+Calc!Y49+Calc!Y52+Calc!Y55+Calc!Y58 -> 6579.1962 | E13: =Calc!Y60 -> 303.15084 | F13: =Calc!Y61+Calc!Y62+Calc!Y63 -> 2655.4659 | G13: =Calc!Y67 -> 119434.11 | H13: =Calc!Y65 -> 109896.3 | I13: =Calc!Y66 -> 9537.8129 | J13: =Calc!Y73 -> 12707.622 | K13: =Calc!Y74 -> 0 | L13: =Calc!Y75 -> 4800 | M13: =Calc!Y76 -> 97200 | N13: =Calc!Y80 -> 114707.62 | O13: =Calc!Y81 -> 4726.4914 | P13: =Calc!Y82 -> 0.95699135 | Q13: =Calc!Y83 -> 0.8936014 | R13: =Calc!Y84 -> 0.10910125 | S13: =Calc!Y85 -> 0.2
A14: 2035 | B14: =Calc!Z8+Calc!Z13+Calc!Z18+Calc!Z23+Calc!Z28+Calc!Z33 -> 107091.12 | C14: =Calc!Z39 -> 19352.181 | D14: =Calc!Z43+Calc!Z46+Calc!Z49+Calc!Z52+Calc!Z55+Calc!Z58 -> 6901.5814 | E14: =Calc!Z60 -> 323.83875 | F14: =Calc!Z61+Calc!Z62+Calc!Z63 -> 2775.6364 | G14: =Calc!Z67 -> 136444.36 | H14: =Calc!Z65 -> 126443.3 | I14: =Calc!Z66 -> 10001.057 | J14: =Calc!Z73 -> 18169.072 | K14: =Calc!Z74 -> 0 | L14: =Calc!Z75 -> 6000 | M14: =Calc!Z76 -> 102000 | N14: =Calc!Z80 -> 126169.07 | O14: =Calc!Z81 -> 10275.289 | P14: =Calc!Z82 -> 0.918736 | Q14: =Calc!Z83 -> 0.86683897 | R14: =Calc!Z84 -> 0.13625623 | S14: =Calc!Z85 -> 0.2
A15: 2036 | B15: =Calc!AA8+Calc!AA13+Calc!AA18+Calc!AA23+Calc!AA28+Calc!AA33 -> 126773.83 | C15: =Calc!AA39 -> 19272.481 | D15: =Calc!AA43+Calc!AA46+Calc!AA49+Calc!AA52+Calc!AA55+Calc!AA58 -> 7243.6575 | E15: =Calc!AA60 -> 354.23607 | F15: =Calc!AA61+Calc!AA62+Calc!AA63 -> 2929.0079 | G15: =Calc!AA67 -> 156573.22 | H15: =Calc!AA65 -> 146046.31 | I15: =Calc!AA66 -> 10526.901 | J15: =Calc!AA73 -> 23591.352 | K15: =Calc!AA74 -> 0 | L15: =Calc!AA75 -> 7200 | M15: =Calc!AA76 -> 107400 | N15: =Calc!AA80 -> 138191.35 | O15: =Calc!AA81 -> 18381.864 | P15: =Calc!AA82 -> 0.87413675 | Q15: =Calc!AA83 -> 0.84932703 | R15: =Calc!AA84 -> 0.15390017 | S15: =Calc!AA85 -> 0.2
A16: 2037 | B16: =Calc!AB8+Calc!AB13+Calc!AB18+Calc!AB23+Calc!AB28+Calc!AB33 -> 148410.5 | C16: =Calc!AB39 -> 19795.426 | D16: =Calc!AB43+Calc!AB46+Calc!AB49+Calc!AB52+Calc!AB55+Calc!AB58 -> 7589.9424 | E16: =Calc!AB60 -> 384.6334 | F16: =Calc!AB61+Calc!AB62+Calc!AB63 -> 3082.3793 | G16: =Calc!AB67 -> 179262.88 | H16: =Calc!AB65 -> 168205.92 | I16: =Calc!AB66 -> 11056.955 | J16: =Calc!AB73 -> 30247.889 | K16: =Calc!AB74 -> 0 | L16: =Calc!AB75 -> 8400 | M16: =Calc!AB76 -> 112800 | N16: =Calc!AB80 -> 151447.89 | O16: =Calc!AB81 -> 27814.989 | P16: =Calc!AB82 -> 0.83463728 | Q16: =Calc!AB83 -> 0.83126518 | R16: =Calc!AB84 -> 0.17206257 | S16: =Calc!AB85 -> 0.2
A17: 2038 | B17: =Calc!AC8+Calc!AC13+Calc!AC18+Calc!AC23+Calc!AC28+Calc!AC33 -> 172077.03 | C17: =Calc!AC39 -> 22314.488 | D17: =Calc!AC43+Calc!AC46+Calc!AC49+Calc!AC52+Calc!AC55+Calc!AC58 -> 7940.4362 | E17: =Calc!AC60 -> 415.03072 | F17: =Calc!AC61+Calc!AC62+Calc!AC63 -> 3235.7507 | G17: =Calc!AC67 -> 205982.74 | H17: =Calc!AC65 -> 194391.52 | I17: =Calc!AC66 -> 11591.218 | J17: =Calc!AC73 -> 39384.291 | K17: =Calc!AC74 -> 0 | L17: =Calc!AC75 -> 9600 | M17: =Calc!AC76 -> 118200 | N17: =Calc!AC80 -> 167184.29 | O17: =Calc!AC81 -> 38798.45 | P17: =Calc!AC82 -> 0.80041079 | Q17: =Calc!AC83 -> 0.8087981 | R17: =Calc!AC84 -> 0.19465185 | S17: =Calc!AC85 -> 0.2
A18: 2039 | B18: =Calc!AD8+Calc!AD13+Calc!AD18+Calc!AD23+Calc!AD28+Calc!AD33 -> 197848.88 | C18: =Calc!AD39 -> 24785.439 | D18: =Calc!AD43+Calc!AD46+Calc!AD49+Calc!AD52+Calc!AD55+Calc!AD58 -> 8295.1389 | E18: =Calc!AD60 -> 445.42804 | F18: =Calc!AD61+Calc!AD62+Calc!AD63 -> 3389.1222 | G18: =Calc!AD67 -> 234764.01 | H18: =Calc!AD65 -> 222634.32 | I18: =Calc!AD66 -> 12129.689 | J18: =Calc!AD73 -> 49799.105 | K18: =Calc!AD74 -> 480 | L18: =Calc!AD75 -> 10800 | M18: =Calc!AD76 -> 123600 | N18: =Calc!AD80 -> 184679.1 | O18: =Calc!AD81 -> 50084.9 | P18: =Calc!AD82 -> 0.77503513 | Q18: =Calc!AD83 -> 0.78583129 | R18: =Calc!AD84 -> 0.2156464 | S18: =Calc!AD85 -> 0.2
A19: 2040 | B19: =Calc!AE8+Calc!AE13+Calc!AE18+Calc!AE23+Calc!AE28+Calc!AE33 -> 225800.97 | C19: =Calc!AE39 -> 27208.278 | D19: =Calc!AE43+Calc!AE46+Calc!AE49+Calc!AE52+Calc!AE55+Calc!AE58 -> 8654.0503 | E19: =Calc!AE60 -> 475.82537 | F19: =Calc!AE61+Calc!AE62+Calc!AE63 -> 3542.4936 | G19: =Calc!AE67 -> 265681.61 | H19: =Calc!AE65 -> 253009.24 | I19: =Calc!AE66 -> 12672.369 | J19: =Calc!AE73 -> 61140.278 | K19: =Calc!AE74 -> 600 | L19: =Calc!AE75 -> 12000 | M19: =Calc!AE76 -> 129000 | N19: =Calc!AE80 -> 202740.28 | O19: =Calc!AE81 -> 62941.335 | P19: =Calc!AE82 -> 0.75122911 | Q19: =Calc!AE83 -> 0.76761554 | R19: =Calc!AE84 -> 0.23366012 | S19: =Calc!AE85 -> 0.2

Sheet Assumptions
A1: Key | B1: Param | C1: Sub_Sector | D1: Scenario | E1: Y2025 | F1: Y2030 | G1: Y2035 | H1: Y2040 | I1: Unit | J1: Source_ID | K1: Note
A2: =B2&"|"&C2&"|"&D2 -> Market_Units|EV_2W|All | B2: Market_Units | C2: EV_2W | D2: All | E2: 20033000 | F2: 24373208 | G2: 29653734 | H2: 36078301 | I2: vehicles/yr | J2: S07; S08; S10; A00 | K2: 2025 from Ref_Base_Year_2025; grows 4%/yr
A3: =B3&"|"&C3&"|"&D3 -> Market_Units|EV_3W_L5|All | B3: Market_Units | C3: EV_3W_L5 | D3: All | E3: 822000 | F3: 952923.29 | G3: 1104699.3 | H3: 1280649.2 | I3: vehicles/yr | J3: S07; S08; S10; A00 | K3: 2025 from Ref_Base_Year_2025; grows 3%/yr
A4: =B4&"|"&C4&"|"&D4 -> Market_Units|EV_3W_L3|All | B4: Market_Units | C4: EV_3W_L3 | D4: All | E4: 616000 | F4: 680113.77 | G4: 750900.56 | H4: 829054.9 | I4: vehicles/yr | J4: S07; S08; S10; A00 | K4: 2025 from Ref_Base_Year_2025; grows 2%/yr
A5: =B5&"|"&C5&"|"&D5 -> Market_Units|EV_4W|All | B5: Market_Units | C5: EV_4W | D5: All | E5: 4449000 | F5: 5678176.7 | G5: 7246952.2 | H5: 9249151.5 | I5: vehicles/yr | J5: S07; S08; S10; A00 | K5: 2025 from Ref_Base_Year_2025; grows 5%/yr
A6: =B6&"|"&C6&"|"&D6 -> Market_Units|EV_Bus|All | B6: Market_Units | C6: EV_Bus | D6: All | E6: 100000 | F6: 121665.29 | G6: 148024.43 | H6: 180094.35 | I6: vehicles/yr | J6: S07; S08; S10; A00 | K6: 2025 from Ref_Base_Year_2025; grows 4%/yr
A7: =B7&"|"&C7&"|"&D7 -> Market_Units|EV_Truck|All | B7: Market_Units | C7: EV_Truck | D7: All | E7: 945000 | F7: 1206086.1 | G7: 1539305.4 | H7: 1964587.1 | I7: vehicles/yr | J7: S07; S08; S10; A00 | K7: 2025 from Ref_Base_Year_2025; grows 5%/yr
A8: =B8&"|"&C8&"|"&D8 -> EV_Share|EV_2W|Low | B8: EV_Share | C8: EV_2W | D8: Low | E8: 0.078 | F8: 0.15 | G8: 0.25 | H8: 0.4 | I8: share of sales | J8: S08; S25; A00 | K8: High tracks the NITI Aayog 2030 ambition (80% 2W/3W, 30% private cars, 40% buses)
A9: =B9&"|"&C9&"|"&D9 -> EV_Share|EV_2W|Base | B9: EV_Share | C9: EV_2W | D9: Base | E9: 0.078 | F9: 0.3 | G9: 0.55 | H9: 0.75 | I9: share of sales | J9: S08; S25; A00 | K9: High tracks the NITI Aayog 2030 ambition (80% 2W/3W, 30% private cars, 40% buses)
A10: =B10&"|"&C10&"|"&D10 -> EV_Share|EV_2W|High | B10: EV_Share | C10: EV_2W | D10: High | E10: 0.078 | F10: 0.55 | G10: 0.8 | H10: 0.95 | I10: share of sales | J10: S08; S25; A00 | K10: High tracks the NITI Aayog 2030 ambition (80% 2W/3W, 30% private cars, 40% buses)
A11: =B11&"|"&C11&"|"&D11 -> EV_Share|EV_3W_L5|Low | B11: EV_Share | C11: EV_3W_L5 | D11: Low | E11: 0.25 | F11: 0.4 | G11: 0.55 | H11: 0.7 | I11: share of sales | J11: S08; S25; A00 | K11: High tracks the NITI Aayog 2030 ambition (80% 2W/3W, 30% private cars, 40% buses)
A12: =B12&"|"&C12&"|"&D12 -> EV_Share|EV_3W_L5|Base | B12: EV_Share | C12: EV_3W_L5 | D12: Base | E12: 0.25 | F12: 0.55 | G12: 0.75 | H12: 0.9 | I12: share of sales | J12: S08; S25; A00 | K12: High tracks the NITI Aayog 2030 ambition (80% 2W/3W, 30% private cars, 40% buses)
A13: =B13&"|"&C13&"|"&D13 -> EV_Share|EV_3W_L5|High | B13: EV_Share | C13: EV_3W_L5 | D13: High | E13: 0.25 | F13: 0.75 | G13: 0.9 | H13: 1 | I13: share of sales | J13: S08; S25; A00 | K13: High tracks the NITI Aayog 2030 ambition (80% 2W/3W, 30% private cars, 40% buses)
... A28: =B28&"|"&C28&"|"&D28 -> LiIon_Share|EV_3W_L3|High | B28: LiIon_Share | C28: EV_3W_L3 | D28: High | E28: 0.25 | F28: 0.85 | G28: 1 | H28: 1 | I28: share of L3 sales | J28: S27; A00 | K28: ~10% of e-rickshaws were Li-ion in FY2023; rest lead-acid
A29: =B29&"|"&C29&"|"&D29 -> LiIon_Share|EV_2W|All | B29: LiIon_Share | C29: EV_2W | D29: All | E29: 1 | F29: 1 | G29: 1 | H29: 1 | I29: share | J29: A00
A30: =B30&"|"&C30&"|"&D30 -> LiIon_Share|EV_3W_L5|All | B30: LiIon_Share | C30: EV_3W_L5 | D30: All | E30: 1 | F30: 1 | G30: 1 | H30: 1 | I30: share | J30: A00
A31: =B31&"|"&C31&"|"&D31 -> LiIon_Share|EV_4W|All | B31: LiIon_Share | C31: EV_4W | D31: All | E31: 1 | F31: 1 | G31: 1 | H31: 1 | I31: share | J31: A00
A32: =B32&"|"&C32&"|"&D32 -> LiIon_Share|EV_Bus|All | B32: LiIon_Share | C32: EV_Bus | D32: All | E32: 1 | F32: 1 | G32: 1 | H32: 1 | I32: share | J32: A00
A33: =B33&"|"&C33&"|"&D33 -> LiIon_Share|EV_Truck|All | B33: LiIon_Share | C33: EV_Truck | D33: All | E33: 1 | F33: 1 | G33: 1 | H33: 1 | I33: share | J33: A00
A34: =B34&"|"&C34&"|"&D34 -> kWh_per_Unit|EV_2W|All | B34: kWh_per_Unit | C34: EV_2W | D34: All | E34: 2.8 | F34: 3.2 | G34: 3.5 | H34: 3.8 | I34: kWh | J34: S10; A00 | K34: 2025 sizes calibrated so segment GWh shares match IESA CY2025 (4W 40%, 3W 27%, 2W 23%, bus 7.8%)
A35: =B35&"|"&C35&"|"&D35 -> kWh_per_Unit|EV_3W_L5|All | B35: kWh_per_Unit | C35: EV_3W_L5 | D35: All | E35: 8 | F35: 10 | G35: 11 | H35: 12 | I35: kWh | J35: S10; A00 | K35: 2025 sizes calibrated so segment GWh shares match IESA CY2025 (4W 40%, 3W 27%, 2W 23%, bus 7.8%)
A36: =B36&"|"&C36&"|"&D36 -> kWh_per_Unit|EV_3W_L3|All | B36: kWh_per_Unit | C36: EV_3W_L3 | D36: All | E36: 5 | F36: 6 | G36: 6.5 | H36: 7 | I36: kWh | J36: S10; A00 | K36: 2025 sizes calibrated so segment GWh shares match IESA CY2025 (4W 40%, 3W 27%, 2W 23%, bus 7.8%)
A37: =B37&"|"&C37&"|"&D37 -> kWh_per_Unit|EV_4W|All | B37: kWh_per_Unit | C37: EV_4W | D37: All | E37: 38 | F37: 42 | G37: 45 | H37: 48 | I37: kWh | J37: S10; A00 | K37: 2025 sizes calibrated so segment GWh shares match IESA CY2025 (4W 40%, 3W 27%, 2W 23%, bus 7.8%)
A38: =B38&"|"&C38&"|"&D38 -> kWh_per_Unit|EV_Bus|All | B38: kWh_per_Unit | C38: EV_Bus | D38: All | E38: 280 | F38: 320 | G38: 350 | H38: 380 | I38: kWh | J38: S10; A00 | K38: 2025 sizes calibrated so segment GWh shares match IESA CY2025 (4W 40%, 3W 27%, 2W 23%, bus 7.8%)
A39: =B39&"|"&C39&"|"&D39 -> kWh_per_Unit|EV_Truck|All | B39: kWh_per_Unit | C39: EV_Truck | D39: All | E39: 40 | F39: 60 | G39: 90 | H39: 120 | I39: kWh | J39: S10; A00 | K39: 2025 sizes calibrated so segment GWh shares match IESA CY2025 (4W 40%, 3W 27%, 2W 23%, bus 7.8%)
A40: =B40&"|"&C40&"|"&D40 -> LFP_Share|EV_2W|All | B40: LFP_Share | C40: EV_2W | D40: All | E40: 0.6 | F40: 0.7 | G40: 0.75 | H40: 0.8 | I40: share of Li-ion kWh (rest NMC) | J40: A00
A41: =B41&"|"&C41&"|"&D41 -> LFP_Share|EV_3W_L5|All | B41: LFP_Share | C41: EV_3W_L5 | D41: All | E41: 0.9 | F41: 0.95 | G41: 0.95 | H41: 0.95 | I41: share of Li-ion kWh (rest NMC) | J41: A00
A42: =B42&"|"&C42&"|"&D42 -> LFP_Share|EV_3W_L3|All | B42: LFP_Share | C42: EV_3W_L3 | D42: All | E42: 1 | F42: 1 | G42: 1 | H42: 1 | I42: share of Li-ion kWh (rest NMC) | J42: A00
A43: =B43&"|"&C43&"|"&D43 -> LFP_Share|EV_4W|All | B43: LFP_Share | C43: EV_4W | D43: All | E43: 0.45 | F43: 0.6 | G43: 0.65 | H43: 0.7 | I43: share of Li-ion kWh (rest NMC) | J43: A00
A44: =B44&"|"&C44&"|"&D44 -> LFP_Share|EV_Bus|All | B44: LFP_Share | C44: EV_Bus | D44: All | E44: 0.9 | F44: 0.95 | G44: 0.95 | H44: 0.95 | I44: share of Li-ion kWh (rest NMC) | J44: A00
A45: =B45&"|"&C45&"|"&D45 -> LFP_Share|EV_Truck|All | B45: LFP_Share | C45: EV_Truck | D45: All | E45: 0.8 | F45: 0.85 | G45: 0.9 | H45: 0.9 | I45: share of Li-ion kWh (rest NMC) | J45: A00
A46: =B46&"|"&C46&"|"&D46 -> LFP_Share|BESS|All | B46: LFP_Share | C46: BESS | D46: All | E46: 1 | F46: 1 | G46: 1 | H46: 1 | I46: share of Li-ion kWh (rest NMC) | J46: A00
A47: =B47&"|"&C47&"|"&D47 -> NaIon_Share|EV_2W|All | B47: NaIon_Share | C47: EV_2W | D47: All | E47: 0 | F47: 0.03 | G47: 0.08 | H47: 0.12 | I47: share of kWh | J47: A00 | K47: Sodium-ion enters low-range 2W/3W and storage first
A48: =B48&"|"&C48&"|"&D48 -> NaIon_Share|EV_3W_L5|All | B48: NaIon_Share | C48: EV_3W_L5 | D48: All | E48: 0 | F48: 0.03 | G48: 0.08 | H48: 0.12 | I48: share of kWh | J48: A00 | K48: Sodium-ion enters low-range 2W/3W and storage first
A49: =B49&"|"&C49&"|"&D49 -> NaIon_Share|EV_3W_L3|All | B49: NaIon_Share | C49: EV_3W_L3 | D49: All | E49: 0 | F49: 0.03 | G49: 0.08 | H49: 0.12 | I49: share of kWh | J49: A00 | K49: Sodium-ion enters low-range 2W/3W and storage first
A50: =B50&"|"&C50&"|"&D50 -> NaIon_Share|BESS|All | B50: NaIon_Share | C50: BESS | D50: All | E50: 0 | F50: 0.03 | G50: 0.08 | H50: 0.12 | I50: share of kWh | J50: A00 | K50: Sodium-ion enters low-range 2W/3W and storage first
A51: =B51&"|"&C51&"|"&D51 -> BESS_Cumulative_GWh|BESS|Low | B51: BESS_Cumulative_GWh | C51: BESS | D51: Low | E51: 4 | F51: 60 | G51: 200 | H51: 320 | I51: GWh installed | J51: S11; S12; A00 | K51: CEA NEP: 193-335 GWh by FY2032 (base 236); 4.7 GWh operating and 35 GWh awarded by May 2026
A52: =B52&"|"&C52&"|"&D52 -> BESS_Cumulative_GWh|BESS|Base | B52: BESS_Cumulative_GWh | C52: BESS | D52: Base | E52: 4 | F52: 110 | G52: 300 | H52: 500 | I52: GWh installed | J52: S11; S12; A00 | K52: CEA NEP: 193-335 GWh by FY2032 (base 236); 4.7 GWh operating and 35 GWh awarded by May 2026
A53: =B53&"|"&C53&"|"&D53 -> BESS_Cumulative_GWh|BESS|High | B53: BESS_Cumulative_GWh | C53: BESS | D53: High | E53: 4 | F53: 180 | G53: 420 | H53: 750 | I53: GWh installed | J53: S11; S12; A00 | K53: CEA NEP: 193-335 GWh by FY2032 (base 236); 4.7 GWh operating and 35 GWh awarded by May 2026
A54: =B54&"|"&C54&"|"&D54 -> Units|ELEC_Phone|Low | B54: Units | C54: ELEC_Phone | D54: Low | E54: 152000000 | F54: 1.4455049e+08 | G54: 1.3746608e+08 | H54: 1.3072887e+08 | I54: devices/yr | J54: S13 | K54: grows -1%/yr
A55: =B55&"|"&C55&"|"&D55 -> Units|ELEC_Phone|Base | B55: Units | C55: ELEC_Phone | D55: Base | E55: 152000000 | F55: 1.5975353e+08 | G55: 1.6790256e+08 | H55: 1.7646728e+08 | I55: devices/yr | J55: S13 | K55: grows 1%/yr
A56: =B56&"|"&C56&"|"&D56 -> Units|ELEC_Phone|High | B56: Units | C56: ELEC_Phone | D56: High | E56: 152000000 | F56: 1.7620966e+08 | G56: 2.0427529e+08 | H56: 2.3681105e+08 | I56: devices/yr | J56: S13 | K56: grows 3%/yr
A57: =B57&"|"&C57&"|"&D57 -> Units|ELEC_PC|Low | B57: Units | C57: ELEC_PC | D57: Low | E57: 15900000 | F57: 17554885 | G57: 19382011 | H57: 21399307 | I57: devices/yr | J57: S14 | K57: grows 2%/yr
A58: =B58&"|"&C58&"|"&D58 -> Units|ELEC_PC|Base | B58: Units | C58: ELEC_PC | D58: Base | E58: 15900000 | F58: 19344781 | G58: 23535884 | H58: 28635002 | I58: devices/yr | J58: S14 | K58: grows 4%/yr
... A90: =B90&"|"&C90&"|"&D90 -> Domestic_Mining_t_LCE|Supply|Low | B90: Domestic_Mining_t_LCE | C90: Supply | D90: Low | E90: 0 | F90: 0 | G90: 0 | H90: 0 | I90: t LCE | J90: S02; S20; S24; A00 | K90: start none; Reasi holds ~18,300 t LCE in total; IEA lead time >16 yrs
A91: =B91&"|"&C91&"|"&D91 -> Domestic_Mining_Start|Supply|Low | B91: Domestic_Mining_Start | C91: Supply | D91: Low | E91: 2099 | F91: 2099 | G91: 2099 | H91: 2099 | I91: year | J91: S24; A00
A92: =B92&"|"&C92&"|"&D92 -> Domestic_Mining_t_LCE|Supply|Base | B92: Domestic_Mining_t_LCE | C92: Supply | D92: Base | E92: 0 | F92: 0 | G92: 0 | H92: 600 | I92: t LCE | J92: S02; S20; S24; A00 | K92: start 2039; Reasi holds ~18,300 t LCE in total; IEA lead time >16 yrs
A93: =B93&"|"&C93&"|"&D93 -> Domestic_Mining_Start|Supply|Base | B93: Domestic_Mining_Start | C93: Supply | D93: Base | E93: 2039 | F93: 2039 | G93: 2039 | H93: 2039 | I93: year | J93: S24; A00
A94: =B94&"|"&C94&"|"&D94 -> Domestic_Mining_t_LCE|Supply|High | B94: Domestic_Mining_t_LCE | C94: Supply | D94: High | E94: 0 | F94: 0 | G94: 800 | H94: 2500 | I94: t LCE | J94: S02; S20; S24; A00 | K94: start 2033; Reasi holds ~18,300 t LCE in total; IEA lead time >16 yrs
A95: =B95&"|"&C95&"|"&D95 -> Domestic_Mining_Start|Supply|High | B95: Domestic_Mining_Start | C95: Supply | D95: High | E95: 2033 | F95: 2033 | G95: 2033 | H95: 2033 | I95: year | J95: S24; A00
A96: =B96&"|"&C96&"|"&D96 -> Overseas_Equity_t_LCE|Supply|Low | B96: Overseas_Equity_t_LCE | C96: Supply | D96: Low | E96: 0 | F96: 0 | G96: 0 | H96: 0 | I96: t LCE | J96: S19; A00 | K96: KABIL Catamarca first output targeted Dec 2030
A97: =B97&"|"&C97&"|"&D97 -> Overseas_Equity_Start|Supply|Low | B97: Overseas_Equity_Start | C97: Supply | D97: Low | E97: 2099 | F97: 2099 | G97: 2099 | H97: 2099 | I97: year | J97: S19; A00
A98: =B98&"|"&C98&"|"&D98 -> Overseas_Equity_t_LCE|Supply|Base | B98: Overseas_Equity_t_LCE | C98: Supply | D98: Base | E98: 0 | F98: 0 | G98: 6000 | H98: 12000 | I98: t LCE | J98: S19; A00 | K98: KABIL Catamarca first output targeted Dec 2030
A99: =B99&"|"&C99&"|"&D99 -> Overseas_Equity_Start|Supply|Base | B99: Overseas_Equity_Start | C99: Supply | D99: Base | E99: 2032 | F99: 2032 | G99: 2032 | H99: 2032 | I99: year | J99: S19; A00
A100: =B100&"|"&C100&"|"&D100 -> Overseas_Equity_t_LCE|Supply|High | B100: Overseas_Equity_t_LCE | C100: Supply | D100: High | E100: 0 | F100: 0 | G100: 15000 | H100: 30000 | I100: t LCE | J100: S19; A00 | K100: KABIL Catamarca first output targeted Dec 2030
A101: =B101&"|"&C101&"|"&D101 -> Overseas_Equity_Start|Supply|High | B101: Overseas_Equity_Start | C101: Supply | D101: High | E101: 2031 | F101: 2031 | G101: 2031 | H101: 2031 | I101: year | J101: S19; A00
A102: =B102&"|"&C102&"|"&D102 -> Collection_Rate|EV_BESS|Low | B102: Collection_Rate | C102: EV_BESS | D102: Low | E102: 0.2 | F102: 0.45 | G102: 0.6 | H102: 0.7 | I102: share of retired | J102: S17; A00 | K102: BWMR: 70% EV collection by 2027-28
A103: =B103&"|"&C103&"|"&D103 -> Collection_Rate|EV_BESS|Base | B103: Collection_Rate | C103: EV_BESS | D103: Base | E103: 0.3 | F103: 0.7 | G103: 0.85 | H103: 0.9 | I103: share of retired | J103: S17; A00 | K103: BWMR: 70% EV collection by 2027-28
A104: =B104&"|"&C104&"|"&D104 -> Collection_Rate|EV_BESS|High | B104: Collection_Rate | C104: EV_BESS | D104: High | E104: 0.4 | F104: 0.85 | G104: 0.95 | H104: 0.95 | I104: share of retired | J104: S17; A00 | K104: BWMR: 70% EV collection by 2027-28
A105: =B105&"|"&C105&"|"&D105 -> Collection_Rate|Electronics|Low | B105: Collection_Rate | C105: Electronics | D105: Low | E105: 0.1 | F105: 0.2 | G105: 0.35 | H105: 0.45 | I105: share of retired | J105: A00 | K105: informal sector handles most e-waste today
A106: =B106&"|"&C106&"|"&D106 -> Collection_Rate|Electronics|Base | B106: Collection_Rate | C106: Electronics | D106: Base | E106: 0.15 | F106: 0.35 | G106: 0.55 | H106: 0.7 | I106: share of retired | J106: A00 | K106: informal sector handles most e-waste today
A107: =B107&"|"&C107&"|"&D107 -> Collection_Rate|Electronics|High | B107: Collection_Rate | C107: Electronics | D107: High | E107: 0.2 | F107: 0.5 | G107: 0.75 | H107: 0.85 | I107: share of retired | J107: A00 | K107: informal sector handles most e-waste today
A108: =B108&"|"&C108&"|"&D108 -> Li_Recovery|Recycling|Low | B108: Li_Recovery | C108: Recycling | D108: Low | E108: 0.7 | F108: 0.8 | G108: 0.85 | H108: 0.85 | I108: share of Li recovered | J108: S17; A00 | K108: hydrometallurgy
A109: =B109&"|"&C109&"|"&D109 -> Li_Recovery|Recycling|Base | B109: Li_Recovery | C109: Recycling | D109: Base | E109: 0.8 | F109: 0.9 | G109: 0.92 | H109: 0.92 | I109: share of Li recovered | J109: S17; A00 | K109: hydrometallurgy
A110: =B110&"|"&C110&"|"&D110 -> Li_Recovery|Recycling|High | B110: Li_Recovery | C110: Recycling | D110: High | E110: 0.85 | F110: 0.95 | G110: 0.95 | H110: 0.95 | I110: share of Li recovered | J110: S17; A00 | K110: hydrometallurgy
A111: =B111&"|"&C111&"|"&D111 -> Global_Supply_t_LCE|Supply|All | B111: Global_Supply_t_LCE | C111: Supply | D111: All | E111: 1544000 | F111: 2600000 | G111: 3400000 | H111: 4300000 | I111: t LCE | J111: S01; S22; S23; A00 | K111: 2025 = 290 kt Li (USGS); IEA sees demand x3 to 2040 with a narrowing gap
A112: =B112&"|"&C112&"|"&D112 -> India_Accessible_Share|Supply|All | B112: India_Accessible_Share | C112: Supply | D112: All | E112: 0.03 | F112: 0.03 | G112: 0.03 | H112: 0.03 | I112: share of global supply | J112: A00 | K112: stress-test lever; India is ~3.5% of world GDP and ~1% of lithium use today

Sheet Inputs
A1: Param | B1: Sub_Sector | C1: Row_in_Assumptions | D1: A2025 | E1: A2030 | F1: A2035 | G1: A2040 | H1: 2025 | I1: 2026 | J1: 2027 | K1: 2028 | L1: 2029 | M1: 2030 | N1: 2031 | O1: 2032 | P1: 2033 | Q1: 2034 | R1: 2035 | S1: 2036 | T1: 2037 | U1: 2038 | V1: 2039 | W1: 2040
A2: Market_Units | B2: EV_2W | C2: =IFERROR(MATCH(A2&"|"&B2&"|"&Control!$B$3,Assumptions!$A$2:$A$112,0),MATCH(A2&"|"&B2&"|All",Assumptions!$A$2:$A$112,0)) -> 1 | D2: =INDEX(Assumptions!$E$2:$E$112,$C2) -> 20033000 | E2: =INDEX(Assumptions!$F$2:$F$112,$C2) -> 24373208 | F2: =INDEX(Assumptions!$G$2:$G$112,$C2) -> 29653734 | G2: =INDEX(Assumptions!$H$2:$H$112,$C2) -> 36078301 | H2: =IF(H$1<=2030,$D2+($E2-$D2)*(H$1-2025)/5,IF(H$1<=2035,$E2+($F2-$E2)*(H$1-2030)/5,$F2+($G2-$F2)*(H$1-2035)/5)) -> 20033000 | I2: =IF(I$1<=2030,$D2+($E2-$D2)*(I$1-2025)/5,IF(I$1<=2035,$E2+($F2-$E2)*(I$1-2030)/5,$F2+($G2-$F2)*(I$1-2035)/5)) -> 20901042 | J2: =IF(J$1<=2030,$D2+($E2-$D2)*(J$1-2025)/5,IF(J$1<=2035,$E2+($F2-$E2)*(J$1-2030)/5,$F2+($G2-$F2)*(J$1-2035)/5)) -> 21769083 | K2: =IF(K$1<=2030,$D2+($E2-$D2)*(K$1-2025)/5,IF(K$1<=2035,$E2+($F2-$E2)*(K$1-2030)/5,$F2+($G2-$F2)*(K$1-2035)/5)) -> 22637125 | L2: =IF(L$1<=2030,$D2+($E2-$D2)*(L$1-2025)/5,IF(L$1<=2035,$E2+($F2-$E2)*(L$1-2030)/5,$F2+($G2-$F2)*(L$1-2035)/5)) -> 23505166 | M2: =IF(M$1<=2030,$D2+($E2-$D2)*(M$1-2025)/5,IF(M$1<=2035,$E2+($F2-$E2)*(M$1-2030)/5,$F2+($G2-$F2)*(M$1-2035)/5)) -> 24373208 | N2: =IF(N$1<=2030,$D2+($E2-$D2)*(N$1-2025)/5,IF(N$1<=2035,$E2+($F2-$E2)*(N$1-2030)/5,$F2+($G2-$F2)*(N$1-2035)/5)) -> 25429313 | O2: =IF(O$1<=2030,$D2+($E2-$D2)*(O$1-2025)/5,IF(O$1<=2035,$E2+($F2-$E2)*(O$1-2030)/5,$F2+($G2-$F2)*(O$1-2035)/5)) -> 26485418 | ... W2: =IF(W$1<=2030,$D2+($E2-$D2)*(W$1-2025)/5,IF(W$1<=2035,$E2+($F2-$E2)*(W$1-2030)/5,$F2+($G2-$F2)*(W$1-2035)/5)) -> 36078301
A3: Market_Units | B3: EV_3W_L5 | C3: =IFERROR(MATCH(A3&"|"&B3&"|"&Control!$B$3,Assumptions!$A$2:$A$112,0),MATCH(A3&"|"&B3&"|All",Assumptions!$A$2:$A$112,0)) -> 2 | D3: =INDEX(Assumptions!$E$2:$E$112,$C3) -> 822000 | E3: =INDEX(Assumptions!$F$2:$F$112,$C3) -> 952923.29 | F3: =INDEX(Assumptions!$G$2:$G$112,$C3) -> 1104699.3 | G3: =INDEX(Assumptions!$H$2:$H$112,$C3) -> 1280649.2 | H3: =IF(H$1<=2030,$D3+($E3-$D3)*(H$1-2025)/5,IF(H$1<=2035,$E3+($F3-$E3)*(H$1-2030)/5,$F3+($G3-$F3)*(H$1-2035)/5)) -> 822000 | I3: =IF(I$1<=2030,$D3+($E3-$D3)*(I$1-2025)/5,IF(I$1<=2035,$E3+($F3-$E3)*(I$1-2030)/5,$F3+($G3-$F3)*(I$1-2035)/5)) -> 848184.66 | J3: =IF(J$1<=2030,$D3+($E3-$D3)*(J$1-2025)/5,IF(J$1<=2035,$E3+($F3-$E3)*(J$1-2030)/5,$F3+($G3-$F3)*(J$1-2035)/5)) -> 874369.32 | K3: =IF(K$1<=2030,$D3+($E3-$D3)*(K$1-2025)/5,IF(K$1<=2035,$E3+($F3-$E3)*(K$1-2030)/5,$F3+($G3-$F3)*(K$1-2035)/5)) -> 900553.97 | L3: =IF(L$1<=2030,$D3+($E3-$D3)*(L$1-2025)/5,IF(L$1<=2035,$E3+($F3-$E3)*(L$1-2030)/5,$F3+($G3-$F3)*(L$1-2035)/5)) -> 926738.63 | M3: =IF(M$1<=2030,$D3+($E3-$D3)*(M$1-2025)/5,IF(M$1<=2035,$E3+($F3-$E3)*(M$1-2030)/5,$F3+($G3-$F3)*(M$1-2035)/5)) -> 952923.29 | N3: =IF(N$1<=2030,$D3+($E3-$D3)*(N$1-2025)/5,IF(N$1<=2035,$E3+($F3-$E3)*(N$1-2030)/5,$F3+($G3-$F3)*(N$1-2035)/5)) -> 983278.48 | O3: =IF(O$1<=2030,$D3+($E3-$D3)*(O$1-2025)/5,IF(O$1<=2035,$E3+($F3-$E3)*(O$1-2030)/5,$F3+($G3-$F3)*(O$1-2035)/5)) -> 1013633.7 | ... W3: =IF(W$1<=2030,$D3+($E3-$D3)*(W$1-2025)/5,IF(W$1<=2035,$E3+($F3-$E3)*(W$1-2030)/5,$F3+($G3-$F3)*(W$1-2035)/5)) -> 1280649.2
A4: Market_Units | B4: EV_3W_L3 | C4: =IFERROR(MATCH(A4&"|"&B4&"|"&Control!$B$3,Assumptions!$A$2:$A$112,0),MATCH(A4&"|"&B4&"|All",Assumptions!$A$2:$A$112,0)) -> 3 | D4: =INDEX(Assumptions!$E$2:$E$112,$C4) -> 616000 | E4: =INDEX(Assumptions!$F$2:$F$112,$C4) -> 680113.77 | F4: =INDEX(Assumptions!$G$2:$G$112,$C4) -> 750900.56 | G4: =INDEX(Assumptions!$H$2:$H$112,$C4) -> 829054.9 | H4: =IF(H$1<=2030,$D4+($E4-$D4)*(H$1-2025)/5,IF(H$1<=2035,$E4+($F4-$E4)*(H$1-2030)/5,$F4+($G4-$F4)*(H$1-2035)/5)) -> 616000 | I4: =IF(I$1<=2030,$D4+($E4-$D4)*(I$1-2025)/5,IF(I$1<=2035,$E4+($F4-$E4)*(I$1-2030)/5,$F4+($G4-$F4)*(I$1-2035)/5)) -> 628822.75 | J4: =IF(J$1<=2030,$D4+($E4-$D4)*(J$1-2025)/5,IF(J$1<=2035,$E4+($F4-$E4)*(J$1-2030)/5,$F4+($G4-$F4)*(J$1-2035)/5)) -> 641645.51 | K4: =IF(K$1<=2030,$D4+($E4-$D4)*(K$1-2025)/5,IF(K$1<=2035,$E4+($F4-$E4)*(K$1-2030)/5,$F4+($G4-$F4)*(K$1-2035)/5)) -> 654468.26 | L4: =IF(L$1<=2030,$D4+($E4-$D4)*(L$1-2025)/5,IF(L$1<=2035,$E4+($F4-$E4)*(L$1-2030)/5,$F4+($G4-$F4)*(L$1-2035)/5)) -> 667291.02 | M4: =IF(M$1<=2030,$D4+($E4-$D4)*(M$1-2025)/5,IF(M$1<=2035,$E4+($F4-$E4)*(M$1-2030)/5,$F4+($G4-$F4)*(M$1-2035)/5)) -> 680113.77 | N4: =IF(N$1<=2030,$D4+($E4-$D4)*(N$1-2025)/5,IF(N$1<=2035,$E4+($F4-$E4)*(N$1-2030)/5,$F4+($G4-$F4)*(N$1-2035)/5)) -> 694271.13 | O4: =IF(O$1<=2030,$D4+($E4-$D4)*(O$1-2025)/5,IF(O$1<=2035,$E4+($F4-$E4)*(O$1-2030)/5,$F4+($G4-$F4)*(O$1-2035)/5)) -> 708428.49 | ... W4: =IF(W$1<=2030,$D4+($E4-$D4)*(W$1-2025)/5,IF(W$1<=2035,$E4+($F4-$E4)*(W$1-2030)/5,$F4+($G4-$F4)*(W$1-2035)/5)) -> 829054.9
A5: Market_Units | B5: EV_4W | C5: =IFERROR(MATCH(A5&"|"&B5&"|"&Control!$B$3,Assumptions!$A$2:$A$112,0),MATCH(A5&"|"&B5&"|All",Assumptions!$A$2:$A$112,0)) -> 4 | D5: =INDEX(Assumptions!$E$2:$E$112,$C5) -> 4449000 | E5: =INDEX(Assumptions!$F$2:$F$112,$C5) -> 5678176.7 | F5: =INDEX(Assumptions!$G$2:$G$112,$C5) -> 7246952.2 | G5: =INDEX(Assumptions!$H$2:$H$112,$C5) -> 9249151.5 | H5: =IF(H$1<=2030,$D5+($E5-$D5)*(H$1-2025)/5,IF(H$1<=2035,$E5+($F5-$E5)*(H$1-2030)/5,$F5+($G5-$F5)*(H$1-2035)/5)) -> 4449000 | I5: =IF(I$1<=2030,$D5+($E5-$D5)*(I$1-2025)/5,IF(I$1<=2035,$E5+($F5-$E5)*(I$1-2030)/5,$F5+($G5-$F5)*(I$1-2035)/5)) -> 4694835.3 | J5: =IF(J$1<=2030,$D5+($E5-$D5)*(J$1-2025)/5,IF(J$1<=2035,$E5+($F5-$E5)*(J$1-2030)/5,$F5+($G5-$F5)*(J$1-2035)/5)) -> 4940670.7 | K5: =IF(K$1<=2030,$D5+($E5-$D5)*(K$1-2025)/5,IF(K$1<=2035,$E5+($F5-$E5)*(K$1-2030)/5,$F5+($G5-$F5)*(K$1-2035)/5)) -> 5186506 | L5: =IF(L$1<=2030,$D5+($E5-$D5)*(L$1-2025)/5,IF(L$1<=2035,$E5+($F5-$E5)*(L$1-2030)/5,$F5+($G5-$F5)*(L$1-2035)/5)) -> 5432341.3 | M5: =IF(M$1<=2030,$D5+($E5-$D5)*(M$1-2025)/5,IF(M$1<=2035,$E5+($F5-$E5)*(M$1-2030)/5,$F5+($G5-$F5)*(M$1-2035)/5)) -> 5678176.7 | N5: =IF(N$1<=2030,$D5+($E5-$D5)*(N$1-2025)/5,IF(N$1<=2035,$E5+($F5-$E5)*(N$1-2030)/5,$F5+($G5-$F5)*(N$1-2035)/5)) -> 5991931.8 | O5: =IF(O$1<=2030,$D5+($E5-$D5)*(O$1-2025)/5,IF(O$1<=2035,$E5+($F5-$E5)*(O$1-2030)/5,$F5+($G5-$F5)*(O$1-2035)/5)) -> 6305686.9 | ... W5: =IF(W$1<=2030,$D5+($E5-$D5)*(W$1-2025)/5,IF(W$1<=2035,$E5+($F5-$E5)*(W$1-2030)/5,$F5+($G5-$F5)*(W$1-2035)/5)) -> 9249151.5
A6: Market_Units | B6: EV_Bus | C6: =IFERROR(MATCH(A6&"|"&B6&"|"&Control!$B$3,Assumptions!$A$2:$A$112,0),MATCH(A6&"|"&B6&"|All",Assumptions!$A$2:$A$112,0)) -> 5 | D6: =INDEX(Assumptions!$E$2:$E$112,$C6) -> 100000 | E6: =INDEX(Assumptions!$F$2:$F$112,$C6) -> 121665.29 | F6: =INDEX(Assumptions!$G$2:$G$112,$C6) -> 148024.43 | G6: =INDEX(Assumptions!$H$2:$H$112,$C6) -> 180094.35 | H6: =IF(H$1<=2030,$D6+($E6-$D6)*(H$1-2025)/5,IF(H$1<=2035,$E6+($F6-$E6)*(H$1-2030)/5,$F6+($G6-$F6)*(H$1-2035)/5)) -> 100000 | I6: =IF(I$1<=2030,$D6+($E6-$D6)*(I$1-2025)/5,IF(I$1<=2035,$E6+($F6-$E6)*(I$1-2030)/5,$F6+($G6-$F6)*(I$1-2035)/5)) -> 104333.06 | J6: =IF(J$1<=2030,$D6+($E6-$D6)*(J$1-2025)/5,IF(J$1<=2035,$E6+($F6-$E6)*(J$1-2030)/5,$F6+($G6-$F6)*(J$1-2035)/5)) -> 108666.12 | K6: =IF(K$1<=2030,$D6+($E6-$D6)*(K$1-2025)/5,IF(K$1<=2035,$E6+($F6-$E6)*(K$1-2030)/5,$F6+($G6-$F6)*(K$1-2035)/5)) -> 112999.17 | L6: =IF(L$1<=2030,$D6+($E6-$D6)*(L$1-2025)/5,IF(L$1<=2035,$E6+($F6-$E6)*(L$1-2030)/5,$F6+($G6-$F6)*(L$1-2035)/5)) -> 117332.23 | M6: =IF(M$1<=2030,$D6+($E6-$D6)*(M$1-2025)/5,IF(M$1<=2035,$E6+($F6-$E6)*(M$1-2030)/5,$F6+($G6-$F6)*(M$1-2035)/5)) -> 121665.29 | N6: =IF(N$1<=2030,$D6+($E6-$D6)*(N$1-2025)/5,IF(N$1<=2035,$E6+($F6-$E6)*(N$1-2030)/5,$F6+($G6-$F6)*(N$1-2035)/5)) -> 126937.12 | O6: =IF(O$1<=2030,$D6+($E6-$D6)*(O$1-2025)/5,IF(O$1<=2035,$E6+($F6-$E6)*(O$1-2030)/5,$F6+($G6-$F6)*(O$1-2035)/5)) -> 132208.95 | ... W6: =IF(W$1<=2030,$D6+($E6-$D6)*(W$1-2025)/5,IF(W$1<=2035,$E6+($F6-$E6)*(W$1-2030)/5,$F6+($G6-$F6)*(W$1-2035)/5)) -> 180094.35
A7: Market_Units | B7: EV_Truck | C7: =IFERROR(MATCH(A7&"|"&B7&"|"&Control!$B$3,Assumptions!$A$2:$A$112,0),MATCH(A7&"|"&B7&"|All",Assumptions!$A$2:$A$112,0)) -> 6 | D7: =INDEX(Assumptions!$E$2:$E$112,$C7) -> 945000 | E7: =INDEX(Assumptions!$F$2:$F$112,$C7) -> 1206086.1 | F7: =INDEX(Assumptions!$G$2:$G$112,$C7) -> 1539305.4 | G7: =INDEX(Assumptions!$H$2:$H$112,$C7) -> 1964587.1 | H7: =IF(H$1<=2030,$D7+($E7-$D7)*(H$1-2025)/5,IF(H$1<=2035,$E7+($F7-$E7)*(H$1-2030)/5,$F7+($G7-$F7)*(H$1-2035)/5)) -> 945000 | I7: =IF(I$1<=2030,$D7+($E7-$D7)*(I$1-2025)/5,IF(I$1<=2035,$E7+($F7-$E7)*(I$1-2030)/5,$F7+($G7-$F7)*(I$1-2035)/5)) -> 997217.22 | J7: =IF(J$1<=2030,$D7+($E7-$D7)*(J$1-2025)/5,IF(J$1<=2035,$E7+($F7-$E7)*(J$1-2030)/5,$F7+($G7-$F7)*(J$1-2035)/5)) -> 1049434.4 | K7: =IF(K$1<=2030,$D7+($E7-$D7)*(K$1-2025)/5,IF(K$1<=2035,$E7+($F7-$E7)*(K$1-2030)/5,$F7+($G7-$F7)*(K$1-2035)/5)) -> 1101651.6 | L7: =IF(L$1<=2030,$D7+($E7-$D7)*(L$1-2025)/5,IF(L$1<=2035,$E7+($F7-$E7)*(L$1-2030)/5,$F7+($G7-$F7)*(L$1-2035)/5)) -> 1153868.9 | M7: =IF(M$1<=2030,$D7+($E7-$D7)*(M$1-2025)/5,IF(M$1<=2035,$E7+($F7-$E7)*(M$1-2030)/5,$F7+($G7-$F7)*(M$1-2035)/5)) -> 1206086.1 | N7: =IF(N$1<=2030,$D7+($E7-$D7)*(N$1-2025)/5,IF(N$1<=2035,$E7+($F7-$E7)*(N$1-2030)/5,$F7+($G7-$F7)*(N$1-2035)/5)) -> 1272729.9 | O7: =IF(O$1<=2030,$D7+($E7-$D7)*(O$1-2025)/5,IF(O$1<=2035,$E7+($F7-$E7)*(O$1-2030)/5,$F7+($G7-$F7)*(O$1-2035)/5)) -> 1339373.8 | ... W7: =IF(W$1<=2030,$D7+($E7-$D7)*(W$1-2025)/5,IF(W$1<=2035,$E7+($F7-$E7)*(W$1-2030)/5,$F7+($G7-$F7)*(W$1-2035)/5)) -> 1964587.1
A8: EV_Share | B8: EV_2W | C8: =IFERROR(MATCH(A8&"|"&B8&"|"&Control!$B$3,Assumptions!$A$2:$A$112,0),MATCH(A8&"|"&B8&"|All",Assumptions!$A$2:$A$112,0)) -> 8 | D8: =INDEX(Assumptions!$E$2:$E$112,$C8) -> 0.078 | E8: =INDEX(Assumptions!$F$2:$F$112,$C8) -> 0.3 | F8: =INDEX(Assumptions!$G$2:$G$112,$C8) -> 0.55 | G8: =INDEX(Assumptions!$H$2:$H$112,$C8) -> 0.75 | H8: =IF(H$1<=2030,$D8+($E8-$D8)*(H$1-2025)/5,IF(H$1<=2035,$E8+($F8-$E8)*(H$1-2030)/5,$F8+($G8-$F8)*(H$1-2035)/5)) -> 0.078 | I8: =IF(I$1<=2030,$D8+($E8-$D8)*(I$1-2025)/5,IF(I$1<=2035,$E8+($F8-$E8)*(I$1-2030)/5,$F8+($G8-$F8)*(I$1-2035)/5)) -> 0.1224 | J8: =IF(J$1<=2030,$D8+($E8-$D8)*(J$1-2025)/5,IF(J$1<=2035,$E8+($F8-$E8)*(J$1-2030)/5,$F8+($G8-$F8)*(J$1-2035)/5)) -> 0.1668 | K8: =IF(K$1<=2030,$D8+($E8-$D8)*(K$1-2025)/5,IF(K$1<=2035,$E8+($F8-$E8)*(K$1-2030)/5,$F8+($G8-$F8)*(K$1-2035)/5)) -> 0.2112 | L8: =IF(L$1<=2030,$D8+($E8-$D8)*(L$1-2025)/5,IF(L$1<=2035,$E8+($F8-$E8)*(L$1-2030)/5,$F8+($G8-$F8)*(L$1-2035)/5)) -> 0.2556 | M8: =IF(M$1<=2030,$D8+($E8-$D8)*(M$1-2025)/5,IF(M$1<=2035,$E8+($F8-$E8)*(M$1-2030)/5,$F8+($G8-$F8)*(M$1-2035)/5)) -> 0.3 | N8: =IF(N$1<=2030,$D8+($E8-$D8)*(N$1-2025)/5,IF(N$1<=2035,$E8+($F8-$E8)*(N$1-2030)/5,$F8+($G8-$F8)*(N$1-2035)/5)) -> 0.35 | O8: =IF(O$1<=2030,$D8+($E8-$D8)*(O$1-2025)/5,IF(O$1<=2035,$E8+($F8-$E8)*(O$1-2030)/5,$F8+($G8-$F8)*(O$1-2035)/5)) -> 0.4 | ... W8: =IF(W$1<=2030,$D8+($E8-$D8)*(W$1-2025)/5,IF(W$1<=2035,$E8+($F8-$E8)*(W$1-2030)/5,$F8+($G8-$F8)*(W$1-2035)/5)) -> 0.75
A9: EV_Share | B9: EV_3W_L5 | C9: =IFERROR(MATCH(A9&"|"&B9&"|"&Control!$B$3,Assumptions!$A$2:$A$112,0),MATCH(A9&"|"&B9&"|All",Assumptions!$A$2:$A$112,0)) -> 11 | D9: =INDEX(Assumptions!$E$2:$E$112,$C9) -> 0.25 | E9: =INDEX(Assumptions!$F$2:$F$112,$C9) -> 0.55 | F9: =INDEX(Assumptions!$G$2:$G$112,$C9) -> 0.75 | G9: =INDEX(Assumptions!$H$2:$H$112,$C9) -> 0.9 | H9: =IF(H$1<=2030,$D9+($E9-$D9)*(H$1-2025)/5,IF(H$1<=2035,$E9+($F9-$E9)*(H$1-2030)/5,$F9+($G9-$F9)*(H$1-2035)/5)) -> 0.25 | I9: =IF(I$1<=2030,$D9+($E9-$D9)*(I$1-2025)/5,IF(I$1<=2035,$E9+($F9-$E9)*(I$1-2030)/5,$F9+($G9-$F9)*(I$1-2035)/5)) -> 0.31 | J9: =IF(J$1<=2030,$D9+($E9-$D9)*(J$1-2025)/5,IF(J$1<=2035,$E9+($F9-$E9)*(J$1-2030)/5,$F9+($G9-$F9)*(J$1-2035)/5)) -> 0.37 | K9: =IF(K$1<=2030,$D9+($E9-$D9)*(K$1-2025)/5,IF(K$1<=2035,$E9+($F9-$E9)*(K$1-2030)/5,$F9+($G9-$F9)*(K$1-2035)/5)) -> 0.43 | L9: =IF(L$1<=2030,$D9+($E9-$D9)*(L$1-2025)/5,IF(L$1<=2035,$E9+($F9-$E9)*(L$1-2030)/5,$F9+($G9-$F9)*(L$1-2035)/5)) -> 0.49 | M9: =IF(M$1<=2030,$D9+($E9-$D9)*(M$1-2025)/5,IF(M$1<=2035,$E9+($F9-$E9)*(M$1-2030)/5,$F9+($G9-$F9)*(M$1-2035)/5)) -> 0.55 | N9: =IF(N$1<=2030,$D9+($E9-$D9)*(N$1-2025)/5,IF(N$1<=2035,$E9+($F9-$E9)*(N$1-2030)/5,$F9+($G9-$F9)*(N$1-2035)/5)) -> 0.59 | O9: =IF(O$1<=2030,$D9+($E9-$D9)*(O$1-2025)/5,IF(O$1<=2035,$E9+($F9-$E9)*(O$1-2030)/5,$F9+($G9-$F9)*(O$1-2035)/5)) -> 0.63 | ... W9: =IF(W$1<=2030,$D9+($E9-$D9)*(W$1-2025)/5,IF(W$1<=2035,$E9+($F9-$E9)*(W$1-2030)/5,$F9+($G9-$F9)*(W$1-2035)/5)) -> 0.9
A10: EV_Share | B10: EV_3W_L3 | C10: =IFERROR(MATCH(A10&"|"&B10&"|"&Control!$B$3,Assumptions!$A$2:$A$112,0),MATCH(A10&"|"&B10&"|All",Assumptions!$A$2:$A$112,0)) -> 14 | D10: =INDEX(Assumptions!$E$2:$E$112,$C10) -> 1 | E10: =INDEX(Assumptions!$F$2:$F$112,$C10) -> 1 | F10: =INDEX(Assumptions!$G$2:$G$112,$C10) -> 1 | G10: =INDEX(Assumptions!$H$2:$H$112,$C10) -> 1 | H10: =IF(H$1<=2030,$D10+($E10-$D10)*(H$1-2025)/5,IF(H$1<=2035,$E10+($F10-$E10)*(H$1-2030)/5,$F10+($G10-$F10)*(H$1-2035)/5)) -> 1 | I10: =IF(I$1<=2030,$D10+($E10-$D10)*(I$1-2025)/5,IF(I$1<=2035,$E10+($F10-$E10)*(I$1-2030)/5,$F10+($G10-$F10)*(I$1-2035)/5)) -> 1 | J10: =IF(J$1<=2030,$D10+($E10-$D10)*(J$1-2025)/5,IF(J$1<=2035,$E10+($F10-$E10)*(J$1-2030)/5,$F10+($G10-$F10)*(J$1-2035)/5)) -> 1 | K10: =IF(K$1<=2030,$D10+($E10-$D10)*(K$1-2025)/5,IF(K$1<=2035,$E10+($F10-$E10)*(K$1-2030)/5,$F10+($G10-$F10)*(K$1-2035)/5)) -> 1 | L10: =IF(L$1<=2030,$D10+($E10-$D10)*(L$1-2025)/5,IF(L$1<=2035,$E10+($F10-$E10)*(L$1-2030)/5,$F10+($G10-$F10)*(L$1-2035)/5)) -> 1 | M10: =IF(M$1<=2030,$D10+($E10-$D10)*(M$1-2025)/5,IF(M$1<=2035,$E10+($F10-$E10)*(M$1-2030)/5,$F10+($G10-$F10)*(M$1-2035)/5)) -> 1 | N10: =IF(N$1<=2030,$D10+($E10-$D10)*(N$1-2025)/5,IF(N$1<=2035,$E10+($F10-$E10)*(N$1-2030)/5,$F10+($G10-$F10)*(N$1-2035)/5)) -> 1 | O10: =IF(O$1<=2030,$D10+($E10-$D10)*(O$1-2025)/5,IF(O$1<=2035,$E10+($F10-$E10)*(O$1-2030)/5,$F10+($G10-$F10)*(O$1-2035)/5)) -> 1 | ... W10: =IF(W$1<=2030,$D10+($E10-$D10)*(W$1-2025)/5,IF(W$1<=2035,$E10+($F10-$E10)*(W$1-2030)/5,$F10+($G10-$F10)*(W$1-2035)/5)) -> 1
A11: EV_Share | B11: EV_4W | C11: =IFERROR(MATCH(A11&"|"&B11&"|"&Control!$B$3,Assumptions!$A$2:$A$112,0),MATCH(A11&"|"&B11&"|All",Assumptions!$A$2:$A$112,0)) -> 17 | D11: =INDEX(Assumptions!$E$2:$E$112,$C11) -> 0.045 | E11: =INDEX(Assumptions!$F$2:$F$112,$C11) -> 0.13 | F11: =INDEX(Assumptions!$G$2:$G$112,$C11) -> 0.28 | G11: =INDEX(Assumptions!$H$2:$H$112,$C11) -> 0.45 | H11: =IF(H$1<=2030,$D11+($E11-$D11)*(H$1-2025)/5,IF(H$1<=2035,$E11+($F11-$E11)*(H$1-2030)/5,$F11+($G11-$F11)*(H$1-2035)/5)) -> 0.045 | I11: =IF(I$1<=2030,$D11+($E11-$D11)*(I$1-2025)/5,IF(I$1<=2035,$E11+($F11-$E11)*(I$1-2030)/5,$F11+($G11-$F11)*(I$1-2035)/5)) -> 0.062 | J11: =IF(J$1<=2030,$D11+($E11-$D11)*(J$1-2025)/5,IF(J$1<=2035,$E11+($F11-$E11)*(J$1-2030)/5,$F11+($G11-$F11)*(J$1-2035)/5)) -> 0.079 | K11: =IF(K$1<=2030,$D11+($E11-$D11)*(K$1-2025)/5,IF(K$1<=2035,$E11+($F11-$E11)*(K$1-2030)/5,$F11+($G11-$F11)*(K$1-2035)/5)) -> 0.096 | L11: =IF(L$1<=2030,$D11+($E11-$D11)*(L$1-2025)/5,IF(L$1<=2035,$E11+($F11-$E11)*(L$1-2030)/5,$F11+($G11-$F11)*(L$1-2035)/5)) -> 0.113 | M11: =IF(M$1<=2030,$D11+($E11-$D11)*(M$1-2025)/5,IF(M$1<=2035,$E11+($F11-$E11)*(M$1-2030)/5,$F11+($G11-$F11)*(M$1-2035)/5)) -> 0.13 | N11: =IF(N$1<=2030,$D11+($E11-$D11)*(N$1-2025)/5,IF(N$1<=2035,$E11+($F11-$E11)*(N$1-2030)/5,$F11+($G11-$F11)*(N$1-2035)/5)) -> 0.16 | O11: =IF(O$1<=2030,$D11+($E11-$D11)*(O$1-2025)/5,IF(O$1<=2035,$E11+($F11-$E11)*(O$1-2030)/5,$F11+($G11-$F11)*(O$1-2035)/5)) -> 0.19 | ... W11: =IF(W$1<=2030,$D11+($E11-$D11)*(W$1-2025)/5,IF(W$1<=2035,$E11+($F11-$E11)*(W$1-2030)/5,$F11+($G11-$F11)*(W$1-2035)/5)) -> 0.45
A12: EV_Share | B12: EV_Bus | C12: =IFERROR(MATCH(A12&"|"&B12&"|"&Control!$B$3,Assumptions!$A$2:$A$112,0),MATCH(A12&"|"&B12&"|All",Assumptions!$A$2:$A$112,0)) -> 20 | D12: =INDEX(Assumptions!$E$2:$E$112,$C12) -> 0.052 | E12: =INDEX(Assumptions!$F$2:$F$112,$C12) -> 0.25 | F12: =INDEX(Assumptions!$G$2:$G$112,$C12) -> 0.5 | G12: =INDEX(Assumptions!$H$2:$H$112,$C12) -> 0.75 | H12: =IF(H$1<=2030,$D12+($E12-$D12)*(H$1-2025)/5,IF(H$1<=2035,$E12+($F12-$E12)*(H$1-2030)/5,$F12+($G12-$F12)*(H$1-2035)/5)) -> 0.052 | I12: =IF(I$1<=2030,$D12+($E12-$D12)*(I$1-2025)/5,IF(I$1<=2035,$E12+($F12-$E12)*(I$1-2030)/5,$F12+($G12-$F12)*(I$1-2035)/5)) -> 0.0916 | J12: =IF(J$1<=2030,$D12+($E12-$D12)*(J$1-2025)/5,IF(J$1<=2035,$E12+($F12-$E12)*(J$1-2030)/5,$F12+($G12-$F12)*(J$1-2035)/5)) -> 0.1312 | K12: =IF(K$1<=2030,$D12+($E12-$D12)*(K$1-2025)/5,IF(K$1<=2035,$E12+($F12-$E12)*(K$1-2030)/5,$F12+($G12-$F12)*(K$1-2035)/5)) -> 0.1708 | L12: =IF(L$1<=2030,$D12+($E12-$D12)*(L$1-2025)/5,IF(L$1<=2035,$E12+($F12-$E12)*(L$1-2030)/5,$F12+($G12-$F12)*(L$1-2035)/5)) -> 0.2104 | M12: =IF(M$1<=2030,$D12+($E12-$D12)*(M$1-2025)/5,IF(M$1<=2035,$E12+($F12-$E12)*(M$1-2030)/5,$F12+($G12-$F12)*(M$1-2035)/5)) -> 0.25 | N12: =IF(N$1<=2030,$D12+($E12-$D12)*(N$1-2025)/5,IF(N$1<=2035,$E12+($F12-$E12)*(N$1-2030)/5,$F12+($G12-$F12)*(N$1-2035)/5)) -> 0.3 | O12: =IF(O$1<=2030,$D12+($E12-$D12)*(O$1-2025)/5,IF(O$1<=2035,$E12+($F12-$E12)*(O$1-2030)/5,$F12+($G12-$F12)*(O$1-2035)/5)) -> 0.35 | ... W12: =IF(W$1<=2030,$D12+($E12-$D12)*(W$1-2025)/5,IF(W$1<=2035,$E12+($F12-$E12)*(W$1-2030)/5,$F12+($G12-$F12)*(W$1-2035)/5)) -> 0.75
A13: EV_Share | B13: EV_Truck | C13: =IFERROR(MATCH(A13&"|"&B13&"|"&Control!$B$3,Assumptions!$A$2:$A$112,0),MATCH(A13&"|"&B13&"|All",Assumptions!$A$2:$A$112,0)) -> 23 | D13: =INDEX(Assumptions!$E$2:$E$112,$C13) -> 0.011 | E13: =INDEX(Assumptions!$F$2:$F$112,$C13) -> 0.06 | F13: =INDEX(Assumptions!$G$2:$G$112,$C13) -> 0.15 | G13: =INDEX(Assumptions!$H$2:$H$112,$C13) -> 0.3 | H13: =IF(H$1<=2030,$D13+($E13-$D13)*(H$1-2025)/5,IF(H$1<=2035,$E13+($F13-$E13)*(H$1-2030)/5,$F13+($G13-$F13)*(H$1-2035)/5)) -> 0.011 | I13: =IF(I$1<=2030,$D13+($E13-$D13)*(I$1-2025)/5,IF(I$1<=2035,$E13+($F13-$E13)*(I$1-2030)/5,$F13+($G13-$F13)*(I$1-2035)/5)) -> 0.0208 | J13: =IF(J$1<=2030,$D13+($E13-$D13)*(J$1-2025)/5,IF(J$1<=2035,$E13+($F13-$E13)*(J$1-2030)/5,$F13+($G13-$F13)*(J$1-2035)/5)) -> 0.0306 | K13: =IF(K$1<=2030,$D13+($E13-$D13)*(K$1-2025)/5,IF(K$1<=2035,$E13+($F13-$E13)*(K$1-2030)/5,$F13+($G13-$F13)*(K$1-2035)/5)) -> 0.0404 | L13: =IF(L$1<=2030,$D13+($E13-$D13)*(L$1-2025)/5,IF(L$1<=2035,$E13+($F13-$E13)*(L$1-2030)/5,$F13+($G13-$F13)*(L$1-2035)/5)) -> 0.0502 | M13: =IF(M$1<=2030,$D13+($E13-$D13)*(M$1-2025)/5,IF(M$1<=2035,$E13+($F13-$E13)*(M$1-2030)/5,$F13+($G13-$F13)*(M$1-2035)/5)) -> 0.06 | N13: =IF(N$1<=2030,$D13+($E13-$D13)*(N$1-2025)/5,IF(N$1<=2035,$E13+($F13-$E13)*(N$1-2030)/5,$F13+($G13-$F13)*(N$1-2035)/5)) -> 0.078 | O13: =IF(O$1<=2030,$D13+($E13-$D13)*(O$1-2025)/5,IF(O$1<=2035,$E13+($F13-$E13)*(O$1-2030)/5,$F13+($G13-$F13)*(O$1-2035)/5)) -> 0.096 | ... W13: =IF(W$1<=2030,$D13+($E13-$D13)*(W$1-2025)/5,IF(W$1<=2035,$E13+($F13-$E13)*(W$1-2030)/5,$F13+($G13-$F13)*(W$1-2035)/5)) -> 0.3
... A62: India_Accessible_Share | B62: Supply | C62: =IFERROR(MATCH(A62&"|"&B62&"|"&Control!$B$3,Assumptions!$A$2:$A$112,0),MATCH(A62&"|"&B62&"|All",Assumptions!$A$2:$A$112,0)) -> 111 | D62: =INDEX(Assumptions!$E$2:$E$112,$C62) -> 0.03 | E62: =INDEX(Assumptions!$F$2:$F$112,$C62) -> 0.03 | F62: =INDEX(Assumptions!$G$2:$G$112,$C62) -> 0.03 | G62: =INDEX(Assumptions!$H$2:$H$112,$C62) -> 0.03 | H62: =IF(H$1<=2030,$D62+($E62-$D62)*(H$1-2025)/5,IF(H$1<=2035,$E62+($F62-$E62)*(H$1-2030)/5,$F62+($G62-$F62)*(H$1-2035)/5)) -> 0.03 | I62: =IF(I$1<=2030,$D62+($E62-$D62)*(I$1-2025)/5,IF(I$1<=2035,$E62+($F62-$E62)*(I$1-2030)/5,$F62+($G62-$F62)*(I$1-2035)/5)) -> 0.03 | J62: =IF(J$1<=2030,$D62+($E62-$D62)*(J$1-2025)/5,IF(J$1<=2035,$E62+($F62-$E62)*(J$1-2030)/5,$F62+($G62-$F62)*(J$1-2035)/5)) -> 0.03 | K62: =IF(K$1<=2030,$D62+($E62-$D62)*(K$1-2025)/5,IF(K$1<=2035,$E62+($F62-$E62)*(K$1-2030)/5,$F62+($G62-$F62)*(K$1-2035)/5)) -> 0.03 | L62: =IF(L$1<=2030,$D62+($E62-$D62)*(L$1-2025)/5,IF(L$1<=2035,$E62+($F62-$E62)*(L$1-2030)/5,$F62+($G62-$F62)*(L$1-2035)/5)) -> 0.03 | M62: =IF(M$1<=2030,$D62+($E62-$D62)*(M$1-2025)/5,IF(M$1<=2035,$E62+($F62-$E62)*(M$1-2030)/5,$F62+($G62-$F62)*(M$1-2035)/5)) -> 0.03 | N62: =IF(N$1<=2030,$D62+($E62-$D62)*(N$1-2025)/5,IF(N$1<=2035,$E62+($F62-$E62)*(N$1-2030)/5,$F62+($G62-$F62)*(N$1-2035)/5)) -> 0.03 | O62: =IF(O$1<=2030,$D62+($E62-$D62)*(O$1-2025)/5,IF(O$1<=2035,$E62+($F62-$E62)*(O$1-2030)/5,$F62+($G62-$F62)*(O$1-2035)/5)) -> 0.03 | ... W62: =IF(W$1<=2030,$D62+($E62-$D62)*(W$1-2025)/5,IF(W$1<=2035,$E62+($F62-$E62)*(W$1-2030)/5,$F62+($G62-$F62)*(W$1-2035)/5)) -> 0.03

Sheet History
A1: Sales before 2025, used only to work out what retires into recycling (A00, rounded from S07/S08 FY totals)
B2: 2013 | C2: 2014 | D2: 2015 | E2: 2016 | F2: 2017 | G2: 2018 | H2: 2019 | I2: 2020 | J2: 2021 | K2: 2022 | L2: 2023 | M2: 2024
A3: EV_2W units | B3: 5000 | C3: 10000 | D3: 20000 | E3: 25000 | F3: 30000 | G3: 50000 | H3: 100000 | I3: 100000 | J3: 230000 | K3: 630000 | L3: 860000 | M3: 1140000
A4: EV_3W_L5 units | B4: 0 | C4: 0 | D4: 0 | E4: 0 | F4: 0 | G4: 1000 | H4: 2000 | I4: 3000 | J4: 6000 | K4: 20000 | L4: 60000 | M4: 140000
A5: EV_3W_L3 units | B5: 50000 | C5: 80000 | D5: 120000 | E5: 180000 | F5: 250000 | G5: 300000 | H5: 350000 | I5: 250000 | J5: 300000 | K5: 380000 | L5: 480000 | M5: 520000
A6: EV_4W units | B6: 0 | C6: 0 | D6: 1000 | E6: 1000 | F6: 1500 | G6: 2000 | H6: 2000 | I6: 4000 | J6: 14000 | K6: 38000 | L6: 82000 | M6: 100000
A7: EV_Bus units | B7: 0 | C7: 0 | D7: 0 | E7: 0 | F7: 0 | G7: 300 | H7: 600 | I7: 600 | J7: 1200 | K7: 2000 | L7: 3500 | M7: 4000
A8: EV_Truck units | B8: 0 | C8: 0 | D8: 0 | E8: 0 | F8: 0 | G8: 0 | H8: 0 | I8: 0 | J8: 0 | K8: 1000 | L8: 3000 | M8: 6000
A9: EV_3W_L3 Li-ion share | B9: 0.02 | C9: 0.02 | D9: 0.02 | E9: 0.02 | F9: 0.02 | G9: 0.02 | H9: 0.05 | I9: 0.05 | J9: 0.05 | K9: 0.1 | L9: 0.1 | M9: 0.15
A10: BESS added (GWh) | B10: 0.02 | C10: 0.02 | D10: 0.02 | E10: 0.02 | F10: 0.02 | G10: 0.02 | H10: 0.02 | I10: 0.02 | J10: 0.05 | K10: 0.1 | L10: 0.3 | M10: 0.8

Sheet Calc
A1: Calculation sheet: one block per use, years across. History columns (2013-2024) feed recycling only.
A2: Use | B2: Sub_Sector | C2: Line | D2: 2013 | E2: 2014 | F2: 2015 | G2: 2016 | H2: 2017 | I2: 2018 | J2: 2019 | K2: 2020 | L2: 2021 | M2: 2022 | N2: 2023 | O2: 2024 | P2: 2025 | Q2: 2026 | R2: 2027 | S2: 2028 | T2: 2029 | U2: 2030 | V2: 2031 | W2: 2032 | X2: 2033 | Y2: 2034 | Z2: 2035 | AA2: 2036 | AB2: 2037 | AC2: 2038 | AD2: 2039 | AE2: 2040 | AG2: kg LCE/kWh
A3: Lever | B3: NaIon | C3: Extra sodium-ion share (lever) | P3: =IF(Control!$B$7,IF(2025<=2030,0.15*(2025-2025)/5,IF(2025<=2035,0.15+0.15*(2025-2030)/5,0.3+0.1*(2025-2035)/5)),0) -> 0 | Q3: =IF(Control!$B$7,IF(2026<=2030,0.15*(2026-2025)/5,IF(2026<=2035,0.15+0.15*(2026-2030)/5,0.3+0.1*(2026-2035)/5)),0) -> 0 | R3: =IF(Control!$B$7,IF(2027<=2030,0.15*(2027-2025)/5,IF(2027<=2035,0.15+0.15*(2027-2030)/5,0.3+0.1*(2027-2035)/5)),0) -> 0 | S3: =IF(Control!$B$7,IF(2028<=2030,0.15*(2028-2025)/5,IF(2028<=2035,0.15+0.15*(2028-2030)/5,0.3+0.1*(2028-2035)/5)),0) -> 0 | T3: =IF(Control!$B$7,IF(2029<=2030,0.15*(2029-2025)/5,IF(2029<=2035,0.15+0.15*(2029-2030)/5,0.3+0.1*(2029-2035)/5)),0) -> 0 | U3: =IF(Control!$B$7,IF(2030<=2030,0.15*(2030-2025)/5,IF(2030<=2035,0.15+0.15*(2030-2030)/5,0.3+0.1*(2030-2035)/5)),0) -> 0 | V3: =IF(Control!$B$7,IF(2031<=2030,0.15*(2031-2025)/5,IF(2031<=2035,0.15+0.15*(2031-2030)/5,0.3+0.1*(2031-2035)/5)),0) -> 0 | W3: =IF(Control!$B$7,IF(2032<=2030,0.15*(2032-2025)/5,IF(2032<=2035,0.15+0.15*(2032-2030)/5,0.3+0.1*(2032-2035)/5)),0) -> 0 | X3: =IF(Control!$B$7,IF(2033<=2030,0.15*(2033-2025)/5,IF(2033<=2035,0.15+0.15*(2033-2030)/5,0.3+0.1*(2033-2035)/5)),0) -> 0 | Y3: =IF(Control!$B$7,IF(2034<=2030,0.15*(2034-2025)/5,IF(2034<=2035,0.15+0.15*(2034-2030)/5,0.3+0.1*(2034-2035)/5)),0) -> 0 | Z3: =IF(Control!$B$7,IF(2035<=2030,0.15*(2035-2025)/5,IF(2035<=2035,0.15+0.15*(2035-2030)/5,0.3+0.1*(2035-2035)/5)),0) -> 0 | AA3: =IF(Control!$B$7,IF(2036<=2030,0.15*(2036-2025)/5,IF(2036<=2035,0.15+0.15*(2036-2030)/5,0.3+0.1*(2036-2035)/5)),0) -> 0 | AB3: =IF(Control!$B$7,IF(2037<=2030,0.15*(2037-2025)/5,IF(2037<=2035,0.15+0.15*(2037-2030)/5,0.3+0.1*(2037-2035)/5)),0) -> 0 | AC3: =IF(Control!$B$7,IF(2038<=2030,0.15*(2038-2025)/5,IF(2038<=2035,0.15+0.15*(2038-2030)/5,0.3+0.1*(2038-2035)/5)),0) -> 0 | AD3: =IF(Control!$B$7,IF(2039<=2030,0.15*(2039-2025)/5,IF(2039<=2035,0.15+0.15*(2039-2030)/5,0.3+0.1*(2039-2035)/5)),0) -> 0 | AE3: =IF(Control!$B$7,IF(2040<=2030,0.15*(2040-2025)/5,IF(2040<=2035,0.15+0.15*(2040-2030)/5,0.3+0.1*(2040-2035)/5)),0) -> 0 | AG3: LFP | AH3: 0.5102
AG4: NMC811 | AH4: 0.5852
A5: Electric two-wheelers | B5: EV_2W | C5: Units | D5: =History!$B$3 -> 5000 | E5: =History!$C$3 -> 10000 | F5: =History!$D$3 -> 20000 | G5: =History!$E$3 -> 25000 | H5: =History!$F$3 -> 30000 | I5: =History!$G$3 -> 50000 | J5: =History!$H$3 -> 100000 | K5: =History!$I$3 -> 100000 | L5: =History!$J$3 -> 230000 | M5: =History!$K$3 -> 630000 | N5: =History!$L$3 -> 860000 | O5: =History!$M$3 -> 1140000 | P5: =Inputs!$H$2*Inputs!$H$8 -> 1562574 | Q5: =Inputs!$I$2*Inputs!$I$8 -> 2558287.5 | R5: =Inputs!$J$2*Inputs!$J$8 -> 3631083.1 | S5: =Inputs!$K$2*Inputs!$K$8 -> 4780960.7 | T5: =Inputs!$L$2*Inputs!$L$8 -> 6007920.4 | U5: =Inputs!$M$2*Inputs!$M$8 -> 7311962.3 | V5: =Inputs!$N$2*Inputs!$N$8 -> 8900259.5 | W5: =Inputs!$O$2*Inputs!$O$8 -> 10594167 | X5: =Inputs!$P$2*Inputs!$P$8 -> 12393685 | Y5: =Inputs!$Q$2*Inputs!$Q$8 -> 14298814 | Z5: =Inputs!$R$2*Inputs!$R$8 -> 16309554 | AA5: =Inputs!$S$2*Inputs!$S$8 -> 18253802 | AB5: =Inputs!$T$2*Inputs!$T$8 -> 20300843 | AC5: =Inputs!$U$2*Inputs!$U$8 -> 22450678 | AD5: =Inputs!$V$2*Inputs!$V$8 -> 24703305 | AE5: =Inputs!$W$2*Inputs!$W$8 -> 27058726 | AG5: LCO | AH5: 0.659
A6: Electric two-wheelers | B6: EV_2W | C6: GWh | D6: =D5*1*Inputs!$H$20*0.9/1000000 -> 0.0126 | E6: =E5*1*Inputs!$H$20*0.9/1000000 -> 0.0252 | F6: =F5*1*Inputs!$H$20*0.9/1000000 -> 0.0504 | G6: =G5*1*Inputs!$H$20*0.9/1000000 -> 0.063 | H6: =H5*1*Inputs!$H$20*0.9/1000000 -> 0.0756 | I6: =I5*1*Inputs!$H$20*0.9/1000000 -> 0.126 | J6: =J5*1*Inputs!$H$20*0.9/1000000 -> 0.252 | K6: =K5*1*Inputs!$H$20*0.9/1000000 -> 0.252 | ... O6: =O5*1*Inputs!$H$20*0.9/1000000 -> 2.8728 | P6: =P5*Inputs!$H$15*Inputs!$H$20/1000000 -> 4.3752072 | Q6: =Q5*Inputs!$I$15*Inputs!$I$20/1000000 -> 7.3678679 | R6: =R5*Inputs!$J$15*Inputs!$J$20/1000000 -> 10.748006 | S6: =S5*Inputs!$K$15*Inputs!$K$20/1000000 -> 14.534121 | T6: =T5*Inputs!$L$15*Inputs!$L$20/1000000 -> 18.744712 | U6: =U5*Inputs!$M$15*Inputs!$M$20/1000000 -> 23.398279 | V6: =V5*Inputs!$N$15*Inputs!$N$20/1000000 -> 29.014846 | W6: =W5*Inputs!$O$15*Inputs!$O$20/1000000 -> 35.172635 | X6: =X5*Inputs!$P$15*Inputs!$P$20/1000000 -> 41.890657 | Y6: =Y5*Inputs!$Q$15*Inputs!$Q$20/1000000 -> 49.187921 | Z6: =Z5*Inputs!$R$15*Inputs!$R$20/1000000 -> 57.083437 | AA6: =AA5*Inputs!$S$15*Inputs!$S$20/1000000 -> 64.983535 | AB6: =AB5*Inputs!$T$15*Inputs!$T$20/1000000 -> 73.489053 | AC6: =AC5*Inputs!$U$15*Inputs!$U$20/1000000 -> 82.618494 | AD6: =AD5*Inputs!$V$15*Inputs!$V$20/1000000 -> 92.390362 | AE6: =AE5*Inputs!$W$15*Inputs!$W$20/1000000 -> 102.82316
A7: Electric two-wheelers | B7: EV_2W | C7: kg LCE per kWh | D7: =P7 -> 0.5402 | E7: =P7 -> 0.5402 | F7: =P7 -> 0.5402 | G7: =P7 -> 0.5402 | H7: =P7 -> 0.5402 | I7: =P7 -> 0.5402 | J7: =P7 -> 0.5402 | K7: =P7 -> 0.5402 | L7: =P7 -> 0.5402 | M7: =P7 -> 0.5402 | N7: =P7 -> 0.5402 | O7: =P7 -> 0.5402 | P7: =(1-MIN(0.8,Inputs!$H$33+P3))*(Inputs!$H$26*$AH$3+(1-Inputs!$H$26)*$AH$4) -> 0.5402 | Q7: =(1-MIN(0.8,Inputs!$I$33+Q3))*(Inputs!$I$26*$AH$3+(1-Inputs!$I$26)*$AH$4) -> 0.5354678 | R7: =(1-MIN(0.8,Inputs!$J$33+R3))*(Inputs!$J$26*$AH$3+(1-Inputs!$J$26)*$AH$4) -> 0.5307536 | S7: =(1-MIN(0.8,Inputs!$K$33+S3))*(Inputs!$K$26*$AH$3+(1-Inputs!$K$26)*$AH$4) -> 0.5260574 | T7: =(1-MIN(0.8,Inputs!$L$33+T3))*(Inputs!$L$26*$AH$3+(1-Inputs!$L$26)*$AH$4) -> 0.5213792 | U7: =(1-MIN(0.8,Inputs!$M$33+U3))*(Inputs!$M$26*$AH$3+(1-Inputs!$M$26)*$AH$4) -> 0.516719 | V7: =(1-MIN(0.8,Inputs!$N$33+V3))*(Inputs!$N$26*$AH$3+(1-Inputs!$N$26)*$AH$4) -> 0.510672 | W7: =(1-MIN(0.8,Inputs!$O$33+W3))*(Inputs!$O$26*$AH$3+(1-Inputs!$O$26)*$AH$4) -> 0.50464 | X7: =(1-MIN(0.8,Inputs!$P$33+X3))*(Inputs!$P$26*$AH$3+(1-Inputs!$P$26)*$AH$4) -> 0.498623 | Y7: =(1-MIN(0.8,Inputs!$Q$33+Y3))*(Inputs!$Q$26*$AH$3+(1-Inputs!$Q$26)*$AH$4) -> 0.492621 | Z7: =(1-MIN(0.8,Inputs!$R$33+Z3))*(Inputs!$R$26*$AH$3+(1-Inputs!$R$26)*$AH$4) -> 0.486634 | AA7: =(1-MIN(0.8,Inputs!$S$33+AA3))*(Inputs!$S$26*$AH$3+(1-Inputs!$S$26)*$AH$4) -> 0.4817184 | AB7: =(1-MIN(0.8,Inputs!$T$33+AB3))*(Inputs!$T$26*$AH$3+(1-Inputs!$T$26)*$AH$4) -> 0.4768148 | AC7: =(1-MIN(0.8,Inputs!$U$33+AC3))*(Inputs!$U$26*$AH$3+(1-Inputs!$U$26)*$AH$4) -> 0.4719232 | AD7: =(1-MIN(0.8,Inputs!$V$33+AD3))*(Inputs!$V$26*$AH$3+(1-Inputs!$V$26)*$AH$4) -> 0.4670436 | AE7: =(1-MIN(0.8,Inputs!$W$33+AE3))*(Inputs!$W$26*$AH$3+(1-Inputs!$W$26)*$AH$4) -> 0.462176 | AG7: from Project_I_Data_Cleaning.xlsx, Chemistry tab
A8: Electric two-wheelers | B8: EV_2W | C8: t LCE | D8: =D6*D7*1000 -> 6.80652 | E8: =E6*E7*1000 -> 13.61304 | F8: =F6*F7*1000 -> 27.22608 | G8: =G6*G7*1000 -> 34.0326 | H8: =H6*H7*1000 -> 40.83912 | I8: =I6*I7*1000 -> 68.0652 | J8: =J6*J7*1000 -> 136.1304 | K8: =K6*K7*1000 -> 136.1304 | ... AE8: =AE6*AE7*1000 -> 47522.396
A10: Electric 3W (L5 autos and cargo) | B10: EV_3W_L5 | C10: Units | D10: =History!$B$4 -> 0 | E10: =History!$C$4 -> 0 | F10: =History!$D$4 -> 0 | G10: =History!$E$4 -> 0 | H10: =History!$F$4 -> 0 | I10: =History!$G$4 -> 1000 | J10: =History!$H$4 -> 2000 | K10: =History!$I$4 -> 3000 | L10: =History!$J$4 -> 6000 | M10: =History!$K$4 -> 20000 | N10: =History!$L$4 -> 60000 | O10: =History!$M$4 -> 140000 | P10: =Inputs!$H$3*Inputs!$H$9 -> 205500 | Q10: =Inputs!$I$3*Inputs!$I$9 -> 262937.24 | R10: =Inputs!$J$3*Inputs!$J$9 -> 323516.65 | S10: =Inputs!$K$3*Inputs!$K$9 -> 387238.21 | T10: =Inputs!$L$3*Inputs!$L$9 -> 454101.93 | U10: =Inputs!$M$3*Inputs!$M$9 -> 524107.81 | V10: =Inputs!$N$3*Inputs!$N$9 -> 580134.31 | W10: =Inputs!$O$3*Inputs!$O$9 -> 638589.22 | X10: =Inputs!$P$3*Inputs!$P$9 -> 699472.55 | Y10: =Inputs!$Q$3*Inputs!$Q$9 -> 762784.29 | Z10: =Inputs!$R$3*Inputs!$R$9 -> 828524.45 | AA10: =Inputs!$S$3*Inputs!$S$9 -> 889113.62 | AB10: =Inputs!$T$3*Inputs!$T$9 -> 951814.19 | AC10: =Inputs!$U$3*Inputs!$U$9 -> 1016626.2 | AD10: =Inputs!$V$3*Inputs!$V$9 -> 1083549.5 | AE10: =Inputs!$W$3*Inputs!$W$9 -> 1152584.3
A11: Electric 3W (L5 autos and cargo) | B11: EV_3W_L5 | C11: GWh | D11: =D10*1*Inputs!$H$21*0.9/1000000 -> 0 | E11: =E10*1*Inputs!$H$21*0.9/1000000 -> 0 | F11: =F10*1*Inputs!$H$21*0.9/1000000 -> 0 | G11: =G10*1*Inputs!$H$21*0.9/1000000 -> 0 | H11: =H10*1*Inputs!$H$21*0.9/1000000 -> 0 | I11: =I10*1*Inputs!$H$21*0.9/1000000 -> 0.0072 | J11: =J10*1*Inputs!$H$21*0.9/1000000 -> 0.0144 | K11: =K10*1*Inputs!$H$21*0.9/1000000 -> 0.0216 | ... O11: =O10*1*Inputs!$H$21*0.9/1000000 -> 1.008 | P11: =P10*Inputs!$H$16*Inputs!$H$21/1000000 -> 1.644 | Q11: =Q10*Inputs!$I$16*Inputs!$I$21/1000000 -> 2.2086728 | R11: =R10*Inputs!$J$16*Inputs!$J$21/1000000 -> 2.8469465 | S11: =S10*Inputs!$K$16*Inputs!$K$21/1000000 -> 3.5625915 | T11: =T10*Inputs!$L$16*Inputs!$L$21/1000000 -> 4.3593785 | U11: =U10*Inputs!$M$16*Inputs!$M$21/1000000 -> 5.2410781 | V11: =V10*Inputs!$N$16*Inputs!$N$21/1000000 -> 5.9173699 | W11: =W10*Inputs!$O$16*Inputs!$O$21/1000000 -> 6.6413279 | X11: =X10*Inputs!$P$16*Inputs!$P$21/1000000 -> 7.414409 | Y11: =Y10*Inputs!$Q$16*Inputs!$Q$21/1000000 -> 8.2380703 | Z11: =Z10*Inputs!$R$16*Inputs!$R$21/1000000 -> 9.1137689 | AA11: =AA10*Inputs!$S$16*Inputs!$S$21/1000000 -> 9.9580725 | AB11: =AB10*Inputs!$T$16*Inputs!$T$21/1000000 -> 10.850682 | AC11: =AC10*Inputs!$U$16*Inputs!$U$21/1000000 -> 11.792863 | AD11: =AD10*Inputs!$V$16*Inputs!$V$21/1000000 -> 12.785884 | AE11: =AE10*Inputs!$W$16*Inputs!$W$21/1000000 -> 13.831012
A12: Electric 3W (L5 autos and cargo) | B12: EV_3W_L5 | C12: kg LCE per kWh | D12: =P12 -> 0.5177 | E12: =P12 -> 0.5177 | F12: =P12 -> 0.5177 | G12: =P12 -> 0.5177 | H12: =P12 -> 0.5177 | I12: =P12 -> 0.5177 | J12: =P12 -> 0.5177 | K12: =P12 -> 0.5177 | L12: =P12 -> 0.5177 | M12: =P12 -> 0.5177 | N12: =P12 -> 0.5177 | O12: =P12 -> 0.5177 | P12: =(1-MIN(0.8,Inputs!$H$34+P3))*(Inputs!$H$27*$AH$3+(1-Inputs!$H$27)*$AH$4) -> 0.5177 | Q12: =(1-MIN(0.8,Inputs!$I$34+Q3))*(Inputs!$I$27*$AH$3+(1-Inputs!$I$27)*$AH$4) -> 0.5138483 | R12: =(1-MIN(0.8,Inputs!$J$34+R3))*(Inputs!$J$27*$AH$3+(1-Inputs!$J$27)*$AH$4) -> 0.5100056 | S12: =(1-MIN(0.8,Inputs!$K$34+S3))*(Inputs!$K$27*$AH$3+(1-Inputs!$K$27)*$AH$4) -> 0.5061719 | T12: =(1-MIN(0.8,Inputs!$L$34+T3))*(Inputs!$L$27*$AH$3+(1-Inputs!$L$27)*$AH$4) -> 0.5023472 | U12: =(1-MIN(0.8,Inputs!$M$34+U3))*(Inputs!$M$27*$AH$3+(1-Inputs!$M$27)*$AH$4) -> 0.4985315 | V12: =(1-MIN(0.8,Inputs!$N$34+V3))*(Inputs!$N$27*$AH$3+(1-Inputs!$N$27)*$AH$4) -> 0.493392 | W12: =(1-MIN(0.8,Inputs!$O$34+W3))*(Inputs!$O$27*$AH$3+(1-Inputs!$O$27)*$AH$4) -> 0.4882525 | X12: =(1-MIN(0.8,Inputs!$P$34+X3))*(Inputs!$P$27*$AH$3+(1-Inputs!$P$27)*$AH$4) -> 0.483113 | Y12: =(1-MIN(0.8,Inputs!$Q$34+Y3))*(Inputs!$Q$27*$AH$3+(1-Inputs!$Q$27)*$AH$4) -> 0.4779735 | Z12: =(1-MIN(0.8,Inputs!$R$34+Z3))*(Inputs!$R$27*$AH$3+(1-Inputs!$R$27)*$AH$4) -> 0.472834 | AA12: =(1-MIN(0.8,Inputs!$S$34+AA3))*(Inputs!$S$27*$AH$3+(1-Inputs!$S$27)*$AH$4) -> 0.4687224 | AB12: =(1-MIN(0.8,Inputs!$T$34+AB3))*(Inputs!$T$27*$AH$3+(1-Inputs!$T$27)*$AH$4) -> 0.4646108 | AC12: =(1-MIN(0.8,Inputs!$U$34+AC3))*(Inputs!$U$27*$AH$3+(1-Inputs!$U$27)*$AH$4) -> 0.4604992 | AD12: =(1-MIN(0.8,Inputs!$V$34+AD3))*(Inputs!$V$27*$AH$3+(1-Inputs!$V$27)*$AH$4) -> 0.4563876 | AE12: =(1-MIN(0.8,Inputs!$W$34+AE3))*(Inputs!$W$27*$AH$3+(1-Inputs!$W$27)*$AH$4) -> 0.452276
A13: Electric 3W (L5 autos and cargo) | B13: EV_3W_L5 | C13: t LCE | D13: =D11*D12*1000 -> 0 | E13: =E11*E12*1000 -> 0 | F13: =F11*F12*1000 -> 0 | G13: =G11*G12*1000 -> 0 | H13: =H11*H12*1000 -> 0 | I13: =I11*I12*1000 -> 3.72744 | J13: =J11*J12*1000 -> 7.45488 | K13: =K11*K12*1000 -> 11.18232 | ... AE13: =AE11*AE12*1000 -> 6255.4346
A15: E-rickshaws and e-carts (L3) | B15: EV_3W_L3 | C15: Units | D15: =History!$B$5 -> 50000 | E15: =History!$C$5 -> 80000 | F15: =History!$D$5 -> 120000 | G15: =History!$E$5 -> 180000 | H15: =History!$F$5 -> 250000 | I15: =History!$G$5 -> 300000 | J15: =History!$H$5 -> 350000 | K15: =History!$I$5 -> 250000 | L15: =History!$J$5 -> 300000 | M15: =History!$K$5 -> 380000 | N15: =History!$L$5 -> 480000 | O15: =History!$M$5 -> 520000 | P15: =Inputs!$H$4*Inputs!$H$10 -> 616000 | Q15: =Inputs!$I$4*Inputs!$I$10 -> 628822.75 | R15: =Inputs!$J$4*Inputs!$J$10 -> 641645.51 | S15: =Inputs!$K$4*Inputs!$K$10 -> 654468.26 | T15: =Inputs!$L$4*Inputs!$L$10 -> 667291.02 | U15: =Inputs!$M$4*Inputs!$M$10 -> 680113.77 | V15: =Inputs!$N$4*Inputs!$N$10 -> 694271.13 | W15: =Inputs!$O$4*Inputs!$O$10 -> 708428.49 | X15: =Inputs!$P$4*Inputs!$P$10 -> 722585.85 | Y15: =Inputs!$Q$4*Inputs!$Q$10 -> 736743.21 | Z15: =Inputs!$R$4*Inputs!$R$10 -> 750900.56 | AA15: =Inputs!$S$4*Inputs!$S$10 -> 766531.43 | AB15: =Inputs!$T$4*Inputs!$T$10 -> 782162.3 | AC15: =Inputs!$U$4*Inputs!$U$10 -> 797793.16 | AD15: =Inputs!$V$4*Inputs!$V$10 -> 813424.03 | AE15: =Inputs!$W$4*Inputs!$W$10 -> 829054.9
A16: E-rickshaws and e-carts (L3) | B16: EV_3W_L3 | C16: GWh | D16: =D15*History!$B$9*Inputs!$H$22*0.9/1000000 -> 0.0045 | E16: =E15*History!$C$9*Inputs!$H$22*0.9/1000000 -> 0.0072 | F16: =F15*History!$D$9*Inputs!$H$22*0.9/1000000 -> 0.0108 | G16: =G15*History!$E$9*Inputs!$H$22*0.9/1000000 -> 0.0162 | H16: =H15*History!$F$9*Inputs!$H$22*0.9/1000000 -> 0.0225 | I16: =I15*History!$G$9*Inputs!$H$22*0.9/1000000 -> 0.027 | J16: =J15*History!$H$9*Inputs!$H$22*0.9/1000000 -> 0.07875 | K16: =K15*History!$I$9*Inputs!$H$22*0.9/1000000 -> 0.05625 | L16: =L15*History!$J$9*Inputs!$H$22*0.9/1000000 -> 0.0675 | M16: =M15*History!$K$9*Inputs!$H$22*0.9/1000000 -> 0.171 | N16: =N15*History!$L$9*Inputs!$H$22*0.9/1000000 -> 0.216 | O16: =O15*History!$M$9*Inputs!$H$22*0.9/1000000 -> 0.351 | P16: =P15*Inputs!$H$14*Inputs!$H$22/1000000 -> 0.77 | Q16: =Q15*Inputs!$I$14*Inputs!$I$22/1000000 -> 1.0463611 | R16: =R15*Inputs!$J$14*Inputs!$J$22/1000000 -> 1.3513054 | S16: =S15*Inputs!$K$14*Inputs!$K$22/1000000 -> 1.6859103 | T16: =T15*Inputs!$L$14*Inputs!$L$22/1000000 -> 2.0512526 | U16: =U15*Inputs!$M$14*Inputs!$M$22/1000000 -> 2.4484096 | V16: =V15*Inputs!$N$14*Inputs!$N$22/1000000 -> 2.752785 | W16: =W15*Inputs!$O$14*Inputs!$O$22/1000000 -> 3.0745796 | X16: =X15*Inputs!$P$14*Inputs!$P$22/1000000 -> 3.4142181 | Y16: =Y15*Inputs!$Q$14*Inputs!$Q$22/1000000 -> 3.7721252 | Z16: =Z15*Inputs!$R$14*Inputs!$R$22/1000000 -> 4.1487256 | AA16: =AA15*Inputs!$S$14*Inputs!$S$22/1000000 -> 4.4520145 | AB16: =AB15*Inputs!$T$14*Inputs!$T$22/1000000 -> 4.7688435 | AC16: =AC15*Inputs!$U$14*Inputs!$U$22/1000000 -> 5.0994939 | AD16: =AD15*Inputs!$V$14*Inputs!$V$22/1000000 -> 5.444247 | AE16: =AE15*Inputs!$W$14*Inputs!$W$22/1000000 -> 5.8033843
A17: E-rickshaws and e-carts (L3) | B17: EV_3W_L3 | C17: kg LCE per kWh | D17: =P17 -> 0.5102 | E17: =P17 -> 0.5102 | F17: =P17 -> 0.5102 | G17: =P17 -> 0.5102 | H17: =P17 -> 0.5102 | I17: =P17 -> 0.5102 | J17: =P17 -> 0.5102 | K17: =P17 -> 0.5102 | L17: =P17 -> 0.5102 | M17: =P17 -> 0.5102 | N17: =P17 -> 0.5102 | O17: =P17 -> 0.5102 | P17: =(1-MIN(0.8,Inputs!$H$35+P3))*(Inputs!$H$28*$AH$3+(1-Inputs!$H$28)*$AH$4) -> 0.5102 | Q17: =(1-MIN(0.8,Inputs!$I$35+Q3))*(Inputs!$I$28*$AH$3+(1-Inputs!$I$28)*$AH$4) -> 0.5071388 | R17: =(1-MIN(0.8,Inputs!$J$35+R3))*(Inputs!$J$28*$AH$3+(1-Inputs!$J$28)*$AH$4) -> 0.5040776 | S17: =(1-MIN(0.8,Inputs!$K$35+S3))*(Inputs!$K$28*$AH$3+(1-Inputs!$K$28)*$AH$4) -> 0.5010164 | T17: =(1-MIN(0.8,Inputs!$L$35+T3))*(Inputs!$L$28*$AH$3+(1-Inputs!$L$28)*$AH$4) -> 0.4979552 | U17: =(1-MIN(0.8,Inputs!$M$35+U3))*(Inputs!$M$28*$AH$3+(1-Inputs!$M$28)*$AH$4) -> 0.494894 | V17: =(1-MIN(0.8,Inputs!$N$35+V3))*(Inputs!$N$28*$AH$3+(1-Inputs!$N$28)*$AH$4) -> 0.489792 | W17: =(1-MIN(0.8,Inputs!$O$35+W3))*(Inputs!$O$28*$AH$3+(1-Inputs!$O$28)*$AH$4) -> 0.48469 | X17: =(1-MIN(0.8,Inputs!$P$35+X3))*(Inputs!$P$28*$AH$3+(1-Inputs!$P$28)*$AH$4) -> 0.479588 | Y17: =(1-MIN(0.8,Inputs!$Q$35+Y3))*(Inputs!$Q$28*$AH$3+(1-Inputs!$Q$28)*$AH$4) -> 0.474486 | Z17: =(1-MIN(0.8,Inputs!$R$35+Z3))*(Inputs!$R$28*$AH$3+(1-Inputs!$R$28)*$AH$4) -> 0.469384 | AA17: =(1-MIN(0.8,Inputs!$S$35+AA3))*(Inputs!$S$28*$AH$3+(1-Inputs!$S$28)*$AH$4) -> 0.4653024 | AB17: =(1-MIN(0.8,Inputs!$T$35+AB3))*(Inputs!$T$28*$AH$3+(1-Inputs!$T$28)*$AH$4) -> 0.4612208 | AC17: =(1-MIN(0.8,Inputs!$U$35+AC3))*(Inputs!$U$28*$AH$3+(1-Inputs!$U$28)*$AH$4) -> 0.4571392 | AD17: =(1-MIN(0.8,Inputs!$V$35+AD3))*(Inputs!$V$28*$AH$3+(1-Inputs!$V$28)*$AH$4) -> 0.4530576 | AE17: =(1-MIN(0.8,Inputs!$W$35+AE3))*(Inputs!$W$28*$AH$3+(1-Inputs!$W$28)*$AH$4) -> 0.448976
A18: E-rickshaws and e-carts (L3) | B18: EV_3W_L3 | C18: t LCE | D18: =D16*D17*1000 -> 2.2959 | E18: =E16*E17*1000 -> 3.67344 | F18: =F16*F17*1000 -> 5.51016 | G18: =G16*G17*1000 -> 8.26524 | H18: =H16*H17*1000 -> 11.4795 | I18: =I16*I17*1000 -> 13.7754 | J18: =J16*J17*1000 -> 40.17825 | K18: =K16*K17*1000 -> 28.69875 | ... AE18: =AE16*AE17*1000 -> 2605.5803
A20: Electric cars | B20: EV_4W | C20: Units | D20: =History!$B$6 -> 0 | E20: =History!$C$6 -> 0 | F20: =History!$D$6 -> 1000 | G20: =History!$E$6 -> 1000 | H20: =History!$F$6 -> 1500 | I20: =History!$G$6 -> 2000 | J20: =History!$H$6 -> 2000 | K20: =History!$I$6 -> 4000 | L20: =History!$J$6 -> 14000 | M20: =History!$K$6 -> 38000 | N20: =History!$L$6 -> 82000 | O20: =History!$M$6 -> 100000 | P20: =Inputs!$H$5*Inputs!$H$11 -> 200205 | Q20: =Inputs!$I$5*Inputs!$I$11 -> 291079.79 | R20: =Inputs!$J$5*Inputs!$J$11 -> 390312.98 | S20: =Inputs!$K$5*Inputs!$K$11 -> 497904.58 | T20: =Inputs!$L$5*Inputs!$L$11 -> 613854.57 | U20: =Inputs!$M$5*Inputs!$M$11 -> 738162.97 | V20: =Inputs!$N$5*Inputs!$N$11 -> 958709.08 | W20: =Inputs!$O$5*Inputs!$O$11 -> 1198080.5 | X20: =Inputs!$P$5*Inputs!$P$11 -> 1456277.2 | Y20: =Inputs!$Q$5*Inputs!$Q$11 -> 1733299.3 | Z20: =Inputs!$R$5*Inputs!$R$11 -> 2029146.6 | AA20: =Inputs!$S$5*Inputs!$S$11 -> 2401281.1 | AB20: =Inputs!$T$5*Inputs!$T$11 -> 2800645.5 | AC20: =Inputs!$U$5*Inputs!$U$11 -> 3227239.8 | AD20: =Inputs!$V$5*Inputs!$V$11 -> 3681064 | AE20: =Inputs!$W$5*Inputs!$W$11 -> 4162118.2
A21: Electric cars | B21: EV_4W | C21: GWh | D21: =D20*1*Inputs!$H$23*0.9/1000000 -> 0 | E21: =E20*1*Inputs!$H$23*0.9/1000000 -> 0 | F21: =F20*1*Inputs!$H$23*0.9/1000000 -> 0.0342 | G21: =G20*1*Inputs!$H$23*0.9/1000000 -> 0.0342 | H21: =H20*1*Inputs!$H$23*0.9/1000000 -> 0.0513 | I21: =I20*1*Inputs!$H$23*0.9/1000000 -> 0.0684 | J21: =J20*1*Inputs!$H$23*0.9/1000000 -> 0.0684 | K21: =K20*1*Inputs!$H$23*0.9/1000000 -> 0.1368 | ... O21: =O20*1*Inputs!$H$23*0.9/1000000 -> 3.42 | P21: =P20*Inputs!$H$17*Inputs!$H$23/1000000 -> 7.60779 | Q21: =Q20*Inputs!$I$17*Inputs!$I$23/1000000 -> 11.293896 | R21: =R20*Inputs!$J$17*Inputs!$J$23/1000000 -> 15.456394 | S21: =S20*Inputs!$K$17*Inputs!$K$23/1000000 -> 20.115345 | T21: =T20*Inputs!$L$17*Inputs!$L$23/1000000 -> 25.290808 | U21: =U20*Inputs!$M$17*Inputs!$M$23/1000000 -> 31.002845 | V21: =V20*Inputs!$N$17*Inputs!$N$23/1000000 -> 40.841007 | W21: =W20*Inputs!$O$17*Inputs!$O$23/1000000 -> 51.757078 | X21: =X20*Inputs!$P$17*Inputs!$P$23/1000000 -> 63.784943 | Y21: =Y20*Inputs!$Q$17*Inputs!$Q$23/1000000 -> 76.958488 | Z21: =Z20*Inputs!$R$17*Inputs!$R$23/1000000 -> 91.311598 | AA21: =AA20*Inputs!$S$17*Inputs!$S$23/1000000 -> 109.49842 | AB21: =AB20*Inputs!$T$17*Inputs!$T$23/1000000 -> 129.38982 | AC21: =AC20*Inputs!$U$17*Inputs!$U$23/1000000 -> 151.03482 | AD21: =AD20*Inputs!$V$17*Inputs!$V$23/1000000 -> 174.48244 | AE21: =AE20*Inputs!$W$17*Inputs!$W$23/1000000 -> 199.78167
A22: Electric cars | B22: EV_4W | C22: kg LCE per kWh | D22: =P22 -> 0.55145 | E22: =P22 -> 0.55145 | F22: =P22 -> 0.55145 | G22: =P22 -> 0.55145 | H22: =P22 -> 0.55145 | I22: =P22 -> 0.55145 | J22: =P22 -> 0.55145 | K22: =P22 -> 0.55145 | L22: =P22 -> 0.55145 | M22: =P22 -> 0.55145 | N22: =P22 -> 0.55145 | O22: =P22 -> 0.55145 | P22: =(1-0)*(Inputs!$H$29*$AH$3+(1-Inputs!$H$29)*$AH$4) -> 0.55145 | Q22: =(1-0)*(Inputs!$I$29*$AH$3+(1-Inputs!$I$29)*$AH$4) -> 0.5492 | R22: =(1-0)*(Inputs!$J$29*$AH$3+(1-Inputs!$J$29)*$AH$4) -> 0.54695 | S22: =(1-0)*(Inputs!$K$29*$AH$3+(1-Inputs!$K$29)*$AH$4) -> 0.5447 | T22: =(1-0)*(Inputs!$L$29*$AH$3+(1-Inputs!$L$29)*$AH$4) -> 0.54245 | U22: =(1-0)*(Inputs!$M$29*$AH$3+(1-Inputs!$M$29)*$AH$4) -> 0.5402 | V22: =(1-0)*(Inputs!$N$29*$AH$3+(1-Inputs!$N$29)*$AH$4) -> 0.53945 | W22: =(1-0)*(Inputs!$O$29*$AH$3+(1-Inputs!$O$29)*$AH$4) -> 0.5387 | X22: =(1-0)*(Inputs!$P$29*$AH$3+(1-Inputs!$P$29)*$AH$4) -> 0.53795 | Y22: =(1-0)*(Inputs!$Q$29*$AH$3+(1-Inputs!$Q$29)*$AH$4) -> 0.5372 | Z22: =(1-0)*(Inputs!$R$29*$AH$3+(1-Inputs!$R$29)*$AH$4) -> 0.53645 | AA22: =(1-0)*(Inputs!$S$29*$AH$3+(1-Inputs!$S$29)*$AH$4) -> 0.5357 | AB22: =(1-0)*(Inputs!$T$29*$AH$3+(1-Inputs!$T$29)*$AH$4) -> 0.53495 | AC22: =(1-0)*(Inputs!$U$29*$AH$3+(1-Inputs!$U$29)*$AH$4) -> 0.5342 | AD22: =(1-0)*(Inputs!$V$29*$AH$3+(1-Inputs!$V$29)*$AH$4) -> 0.53345 | AE22: =(1-0)*(Inputs!$W$29*$AH$3+(1-Inputs!$W$29)*$AH$4) -> 0.5327
A23: Electric cars | B23: EV_4W | C23: t LCE | D23: =D21*D22*1000 -> 0 | E23: =E21*E22*1000 -> 0 | F23: =F21*F22*1000 -> 18.85959 | G23: =G21*G22*1000 -> 18.85959 | H23: =H21*H22*1000 -> 28.289385 | I23: =I21*I22*1000 -> 37.71918 | J23: =J21*J22*1000 -> 37.71918 | K23: =K21*K22*1000 -> 75.43836 | ... AE23: =AE21*AE22*1000 -> 106423.7
A25: Electric buses | B25: EV_Bus | C25: Units | D25: =History!$B$7 -> 0 | E25: =History!$C$7 -> 0 | F25: =History!$D$7 -> 0 | G25: =History!$E$7 -> 0 | H25: =History!$F$7 -> 0 | I25: =History!$G$7 -> 300 | J25: =History!$H$7 -> 600 | K25: =History!$I$7 -> 600 | L25: =History!$J$7 -> 1200 | M25: =History!$K$7 -> 2000 | N25: =History!$L$7 -> 3500 | O25: =History!$M$7 -> 4000 | P25: =Inputs!$H$6*Inputs!$H$12 -> 5200 | Q25: =Inputs!$I$6*Inputs!$I$12 -> 9556.9081 | R25: =Inputs!$J$6*Inputs!$J$12 -> 14256.994 | S25: =Inputs!$K$6*Inputs!$K$12 -> 19300.259 | T25: =Inputs!$L$6*Inputs!$L$12 -> 24686.702 | U25: =Inputs!$M$6*Inputs!$M$12 -> 30416.323 | V25: =Inputs!$N$6*Inputs!$N$12 -> 38081.135 | W25: =Inputs!$O$6*Inputs!$O$12 -> 46273.131 | X25: =Inputs!$P$6*Inputs!$P$12 -> 54992.309 | Y25: =Inputs!$Q$6*Inputs!$Q$12 -> 64238.67 | Z25: =Inputs!$R$6*Inputs!$R$12 -> 74012.214 | AA25: =Inputs!$S$6*Inputs!$S$12 -> 84941.127 | AB25: =Inputs!$T$6*Inputs!$T$12 -> 96511.438 | AC25: =Inputs!$U$6*Inputs!$U$12 -> 108723.15 | AD25: =Inputs!$V$6*Inputs!$V$12 -> 121576.26 | AE25: =Inputs!$W$6*Inputs!$W$12 -> 135070.76
A26: Electric buses | B26: EV_Bus | C26: GWh | D26: =D25*1*Inputs!$H$24*0.9/1000000 -> 0 | E26: =E25*1*Inputs!$H$24*0.9/1000000 -> 0 | F26: =F25*1*Inputs!$H$24*0.9/1000000 -> 0 | G26: =G25*1*Inputs!$H$24*0.9/1000000 -> 0 | H26: =H25*1*Inputs!$H$24*0.9/1000000 -> 0 | I26: =I25*1*Inputs!$H$24*0.9/1000000 -> 0.0756 | J26: =J25*1*Inputs!$H$24*0.9/1000000 -> 0.1512 | K26: =K25*1*Inputs!$H$24*0.9/1000000 -> 0.1512 | ... O26: =O25*1*Inputs!$H$24*0.9/1000000 -> 1.008 | P26: =P25*Inputs!$H$18*Inputs!$H$24/1000000 -> 1.456 | Q26: =Q25*Inputs!$I$18*Inputs!$I$24/1000000 -> 2.7523895 | R26: =R25*Inputs!$J$18*Inputs!$J$24/1000000 -> 4.2200704 | S26: =S25*Inputs!$K$18*Inputs!$K$24/1000000 -> 5.8672787 | T26: =T25*Inputs!$L$18*Inputs!$L$24/1000000 -> 7.7022509 | U26: =U25*Inputs!$M$18*Inputs!$M$24/1000000 -> 9.7332232 | V26: =V25*Inputs!$N$18*Inputs!$N$24/1000000 -> 12.41445 | W26: =W25*Inputs!$O$18*Inputs!$O$24/1000000 -> 15.362679 | X26: =X25*Inputs!$P$18*Inputs!$P$24/1000000 -> 18.587401 | Y26: =Y25*Inputs!$Q$18*Inputs!$Q$24/1000000 -> 22.098103 | Z26: =Z25*Inputs!$R$18*Inputs!$R$24/1000000 -> 25.904275 | AA26: =AA25*Inputs!$S$18*Inputs!$S$24/1000000 -> 30.239041 | AB26: =AB25*Inputs!$T$18*Inputs!$T$24/1000000 -> 34.937141 | AC26: =AC25*Inputs!$U$18*Inputs!$U$24/1000000 -> 40.010119 | AD26: =AD25*Inputs!$V$18*Inputs!$V$24/1000000 -> 45.46952 | AE26: =AE25*Inputs!$W$18*Inputs!$W$24/1000000 -> 51.32689
A27: Electric buses | B27: EV_Bus | C27: kg LCE per kWh | D27: =P27 -> 0.5177 | E27: =P27 -> 0.5177 | F27: =P27 -> 0.5177 | G27: =P27 -> 0.5177 | H27: =P27 -> 0.5177 | I27: =P27 -> 0.5177 | J27: =P27 -> 0.5177 | K27: =P27 -> 0.5177 | L27: =P27 -> 0.5177 | M27: =P27 -> 0.5177 | N27: =P27 -> 0.5177 | O27: =P27 -> 0.5177 | P27: =(1-0)*(Inputs!$H$30*$AH$3+(1-Inputs!$H$30)*$AH$4) -> 0.5177 | Q27: =(1-0)*(Inputs!$I$30*$AH$3+(1-Inputs!$I$30)*$AH$4) -> 0.51695 | R27: =(1-0)*(Inputs!$J$30*$AH$3+(1-Inputs!$J$30)*$AH$4) -> 0.5162 | S27: =(1-0)*(Inputs!$K$30*$AH$3+(1-Inputs!$K$30)*$AH$4) -> 0.51545 | T27: =(1-0)*(Inputs!$L$30*$AH$3+(1-Inputs!$L$30)*$AH$4) -> 0.5147 | U27: =(1-0)*(Inputs!$M$30*$AH$3+(1-Inputs!$M$30)*$AH$4) -> 0.51395 | V27: =(1-0)*(Inputs!$N$30*$AH$3+(1-Inputs!$N$30)*$AH$4) -> 0.51395 | W27: =(1-0)*(Inputs!$O$30*$AH$3+(1-Inputs!$O$30)*$AH$4) -> 0.51395 | X27: =(1-0)*(Inputs!$P$30*$AH$3+(1-Inputs!$P$30)*$AH$4) -> 0.51395 | Y27: =(1-0)*(Inputs!$Q$30*$AH$3+(1-Inputs!$Q$30)*$AH$4) -> 0.51395 | Z27: =(1-0)*(Inputs!$R$30*$AH$3+(1-Inputs!$R$30)*$AH$4) -> 0.51395 | AA27: =(1-0)*(Inputs!$S$30*$AH$3+(1-Inputs!$S$30)*$AH$4) -> 0.51395 | AB27: =(1-0)*(Inputs!$T$30*$AH$3+(1-Inputs!$T$30)*$AH$4) -> 0.51395 | AC27: =(1-0)*(Inputs!$U$30*$AH$3+(1-Inputs!$U$30)*$AH$4) -> 0.51395 | AD27: =(1-0)*(Inputs!$V$30*$AH$3+(1-Inputs!$V$30)*$AH$4) -> 0.51395 | AE27: =(1-0)*(Inputs!$W$30*$AH$3+(1-Inputs!$W$30)*$AH$4) -> 0.51395
A28: Electric buses | B28: EV_Bus | C28: t LCE | D28: =D26*D27*1000 -> 0 | E28: =E26*E27*1000 -> 0 | F28: =F26*F27*1000 -> 0 | G28: =G26*G27*1000 -> 0 | H28: =H26*H27*1000 -> 0 | I28: =I26*I27*1000 -> 39.13812 | J28: =J26*J27*1000 -> 78.27624 | K28: =K26*K27*1000 -> 78.27624 | ... AE28: =AE26*AE27*1000 -> 26379.455
A30: Electric trucks and goods carriers | B30: EV_Truck | C30: Units | D30: =History!$B$8 -> 0 | E30: =History!$C$8 -> 0 | F30: =History!$D$8 -> 0 | G30: =History!$E$8 -> 0 | H30: =History!$F$8 -> 0 | I30: =History!$G$8 -> 0 | J30: =History!$H$8 -> 0 | K30: =History!$I$8 -> 0 | L30: =History!$J$8 -> 0 | M30: =History!$K$8 -> 1000 | N30: =History!$L$8 -> 3000 | O30: =History!$M$8 -> 6000 | P30: =Inputs!$H$7*Inputs!$H$13 -> 10395 | Q30: =Inputs!$I$7*Inputs!$I$13 -> 20742.118 | R30: =Inputs!$J$7*Inputs!$J$13 -> 32112.694 | S30: =Inputs!$K$7*Inputs!$K$13 -> 44506.726 | T30: =Inputs!$L$7*Inputs!$L$13 -> 57924.217 | U30: =Inputs!$M$7*Inputs!$M$13 -> 72365.165 | V30: =Inputs!$N$7*Inputs!$N$13 -> 99272.936 | W30: =Inputs!$O$7*Inputs!$O$13 -> 128579.89 | X30: =Inputs!$P$7*Inputs!$P$13 -> 160286.02 | Y30: =Inputs!$Q$7*Inputs!$Q$13 -> 194391.33 | Z30: =Inputs!$R$7*Inputs!$R$13 -> 230895.81 | AA30: =Inputs!$S$7*Inputs!$S$13 -> 292385.12 | AB30: =Inputs!$T$7*Inputs!$T$13 -> 358977.8 | AC30: =Inputs!$U$7*Inputs!$U$13 -> 430673.87 | AD30: =Inputs!$V$7*Inputs!$V$13 -> 507473.31 | AE30: =Inputs!$W$7*Inputs!$W$13 -> 589376.14
A31: Electric trucks and goods carriers | B31: EV_Truck | C31: GWh | D31: =D30*1*Inputs!$H$25*0.9/1000000 -> 0 | E31: =E30*1*Inputs!$H$25*0.9/1000000 -> 0 | F31: =F30*1*Inputs!$H$25*0.9/1000000 -> 0 | G31: =G30*1*Inputs!$H$25*0.9/1000000 -> 0 | H31: =H30*1*Inputs!$H$25*0.9/1000000 -> 0 | I31: =I30*1*Inputs!$H$25*0.9/1000000 -> 0 | J31: =J30*1*Inputs!$H$25*0.9/1000000 -> 0 | K31: =K30*1*Inputs!$H$25*0.9/1000000 -> 0 | ... O31: =O30*1*Inputs!$H$25*0.9/1000000 -> 0.216 | P31: =P30*Inputs!$H$19*Inputs!$H$25/1000000 -> 0.4158 | Q31: =Q30*Inputs!$I$19*Inputs!$I$25/1000000 -> 0.9126532 | R31: =R30*Inputs!$J$19*Inputs!$J$25/1000000 -> 1.5414093 | S31: =S30*Inputs!$K$19*Inputs!$K$25/1000000 -> 2.3143498 | T31: =T30*Inputs!$L$19*Inputs!$L$25/1000000 -> 3.2437561 | U31: =U30*Inputs!$M$19*Inputs!$M$25/1000000 -> 4.3419099 | V31: =V30*Inputs!$N$19*Inputs!$N$25/1000000 -> 6.5520138 | W31: =W30*Inputs!$O$19*Inputs!$O$25/1000000 -> 9.2577518 | X31: =X30*Inputs!$P$19*Inputs!$P$25/1000000 -> 12.502309 | Y31: =Y30*Inputs!$Q$19*Inputs!$Q$25/1000000 -> 16.328871 | Z31: =Z30*Inputs!$R$19*Inputs!$R$25/1000000 -> 20.780623 | AA31: =AA30*Inputs!$S$19*Inputs!$S$25/1000000 -> 28.068971 | AB31: =AB30*Inputs!$T$19*Inputs!$T$25/1000000 -> 36.615736 | AC31: =AC30*Inputs!$U$19*Inputs!$U$25/1000000 -> 46.512778 | AD31: =AD30*Inputs!$V$19*Inputs!$V$25/1000000 -> 57.851958 | AE31: =AE30*Inputs!$W$19*Inputs!$W$25/1000000 -> 70.725137
A32: Electric trucks and goods carriers | B32: EV_Truck | C32: kg LCE per kWh | D32: =P32 -> 0.5252 | E32: =P32 -> 0.5252 | F32: =P32 -> 0.5252 | G32: =P32 -> 0.5252 | H32: =P32 -> 0.5252 | I32: =P32 -> 0.5252 | J32: =P32 -> 0.5252 | K32: =P32 -> 0.5252 | L32: =P32 -> 0.5252 | M32: =P32 -> 0.5252 | N32: =P32 -> 0.5252 | O32: =P32 -> 0.5252 | P32: =(1-0)*(Inputs!$H$31*$AH$3+(1-Inputs!$H$31)*$AH$4) -> 0.5252 | Q32: =(1-0)*(Inputs!$I$31*$AH$3+(1-Inputs!$I$31)*$AH$4) -> 0.52445 | R32: =(1-0)*(Inputs!$J$31*$AH$3+(1-Inputs!$J$31)*$AH$4) -> 0.5237 | S32: =(1-0)*(Inputs!$K$31*$AH$3+(1-Inputs!$K$31)*$AH$4) -> 0.52295 | T32: =(1-0)*(Inputs!$L$31*$AH$3+(1-Inputs!$L$31)*$AH$4) -> 0.5222 | U32: =(1-0)*(Inputs!$M$31*$AH$3+(1-Inputs!$M$31)*$AH$4) -> 0.52145 | V32: =(1-0)*(Inputs!$N$31*$AH$3+(1-Inputs!$N$31)*$AH$4) -> 0.5207 | W32: =(1-0)*(Inputs!$O$31*$AH$3+(1-Inputs!$O$31)*$AH$4) -> 0.51995 | X32: =(1-0)*(Inputs!$P$31*$AH$3+(1-Inputs!$P$31)*$AH$4) -> 0.5192 | Y32: =(1-0)*(Inputs!$Q$31*$AH$3+(1-Inputs!$Q$31)*$AH$4) -> 0.51845 | Z32: =(1-0)*(Inputs!$R$31*$AH$3+(1-Inputs!$R$31)*$AH$4) -> 0.5177 | AA32: =(1-0)*(Inputs!$S$31*$AH$3+(1-Inputs!$S$31)*$AH$4) -> 0.5177 | AB32: =(1-0)*(Inputs!$T$31*$AH$3+(1-Inputs!$T$31)*$AH$4) -> 0.5177 | AC32: =(1-0)*(Inputs!$U$31*$AH$3+(1-Inputs!$U$31)*$AH$4) -> 0.5177 | AD32: =(1-0)*(Inputs!$V$31*$AH$3+(1-Inputs!$V$31)*$AH$4) -> 0.5177 | AE32: =(1-0)*(Inputs!$W$31*$AH$3+(1-Inputs!$W$31)*$AH$4) -> 0.5177
A33: Electric trucks and goods carriers | B33: EV_Truck | C33: t LCE | D33: =D31*D32*1000 -> 0 | E33: =E31*E32*1000 -> 0 | F33: =F31*F32*1000 -> 0 | G33: =G31*G32*1000 -> 0 | H33: =H31*H32*1000 -> 0 | I33: =I31*I32*1000 -> 0 | J33: =J31*J32*1000 -> 0 | K33: =K31*K32*1000 -> 0 | ... AE33: =AE31*AE32*1000 -> 36614.403
A35: Grid battery storage | B35: BESS | C35: Cumulative GWh | P35: =Inputs!$H$37 -> 4 | Q35: =Inputs!$I$37 -> 25.2 | R35: =Inputs!$J$37 -> 46.4 | S35: =Inputs!$K$37 -> 67.6 | T35: =Inputs!$L$37 -> 88.8 | U35: =Inputs!$M$37 -> 110 | V35: =Inputs!$N$37 -> 148 | W35: =Inputs!$O$37 -> 186 | X35: =Inputs!$P$37 -> 224 | Y35: =Inputs!$Q$37 -> 262 | Z35: =Inputs!$R$37 -> 300 | AA35: =Inputs!$S$37 -> 340 | AB35: =Inputs!$T$37 -> 380 | AC35: =Inputs!$U$37 -> 420 | AD35: =Inputs!$V$37 -> 460 | AE35: =Inputs!$W$37 -> 500
A36: Grid battery storage | B36: BESS | C36: New GWh (ramp) | P36: =P35-SUM(History!$B$10:$M$10) -> 2.59 | Q36: =MAX(0,P36+(U35-P35-5*P36)/15*(2026-2025)) -> 8.7933333 | R36: =MAX(0,P36+(U35-P35-5*P36)/15*(2027-2025)) -> 14.996667 | S36: =MAX(0,P36+(U35-P35-5*P36)/15*(2028-2025)) -> 21.2 | T36: =MAX(0,P36+(U35-P35-5*P36)/15*(2029-2025)) -> 27.403333 | U36: =MAX(0,P36+(U35-P35-5*P36)/15*(2030-2025)) -> 33.606667 | V36: =MAX(0,U36+(Z35-U35-5*U36)/15*(2031-2030)) -> 35.071111 | W36: =MAX(0,U36+(Z35-U35-5*U36)/15*(2032-2030)) -> 36.535556 | X36: =MAX(0,U36+(Z35-U35-5*U36)/15*(2033-2030)) -> 38 | Y36: =MAX(0,U36+(Z35-U35-5*U36)/15*(2034-2030)) -> 39.464444 | Z36: =MAX(0,U36+(Z35-U35-5*U36)/15*(2035-2030)) -> 40.928889 | AA36: =MAX(0,Z36+(AE35-Z35-5*Z36)/15*(2036-2035)) -> 40.619259 | AB36: =MAX(0,Z36+(AE35-Z35-5*Z36)/15*(2037-2035)) -> 40.30963 | AC36: =MAX(0,Z36+(AE35-Z35-5*Z36)/15*(2038-2035)) -> 40 | AD36: =MAX(0,Z36+(AE35-Z35-5*Z36)/15*(2039-2035)) -> 39.69037 | AE36: =MAX(0,Z36+(AE35-Z35-5*Z36)/15*(2040-2035)) -> 39.380741
A37: Grid battery storage | B37: BESS | C37: GWh added | D37: =History!$B$10 -> 0.02 | E37: =History!$C$10 -> 0.02 | F37: =History!$D$10 -> 0.02 | G37: =History!$E$10 -> 0.02 | H37: =History!$F$10 -> 0.02 | I37: =History!$G$10 -> 0.02 | J37: =History!$H$10 -> 0.02 | K37: =History!$I$10 -> 0.02 | L37: =History!$J$10 -> 0.05 | M37: =History!$K$10 -> 0.1 | N37: =History!$L$10 -> 0.3 | O37: =History!$M$10 -> 0.8 | P37: =P36+D37 -> 2.61 | Q37: =Q36+E37 -> 8.8133333 | R37: =R36+F37 -> 15.016667 | S37: =S36+G37 -> 21.22 | T37: =T36+H37 -> 27.423333 | U37: =U36+I37 -> 33.626667 | V37: =V36+J37 -> 35.091111 | W37: =W36+K37 -> 36.555556 | ... AE37: =AE36+S37 -> 60.600741
A38: Grid battery storage | B38: BESS | C38: kg LCE per kWh | D38: =$AH$3 -> 0.5102 | E38: =$AH$3 -> 0.5102 | F38: =$AH$3 -> 0.5102 | G38: =$AH$3 -> 0.5102 | H38: =$AH$3 -> 0.5102 | I38: =$AH$3 -> 0.5102 | J38: =$AH$3 -> 0.5102 | K38: =$AH$3 -> 0.5102 | ... O38: =$AH$3 -> 0.5102 | P38: =(1-MIN(0.8,Inputs!$H$36+P3))*$AH$3 -> 0.5102 | Q38: =(1-MIN(0.8,Inputs!$I$36+Q3))*$AH$3 -> 0.5071388 | R38: =(1-MIN(0.8,Inputs!$J$36+R3))*$AH$3 -> 0.5040776 | S38: =(1-MIN(0.8,Inputs!$K$36+S3))*$AH$3 -> 0.5010164 | T38: =(1-MIN(0.8,Inputs!$L$36+T3))*$AH$3 -> 0.4979552 | U38: =(1-MIN(0.8,Inputs!$M$36+U3))*$AH$3 -> 0.494894 | V38: =(1-MIN(0.8,Inputs!$N$36+V3))*$AH$3 -> 0.489792 | W38: =(1-MIN(0.8,Inputs!$O$36+W3))*$AH$3 -> 0.48469 | X38: =(1-MIN(0.8,Inputs!$P$36+X3))*$AH$3 -> 0.479588 | Y38: =(1-MIN(0.8,Inputs!$Q$36+Y3))*$AH$3 -> 0.474486 | Z38: =(1-MIN(0.8,Inputs!$R$36+Z3))*$AH$3 -> 0.469384 | AA38: =(1-MIN(0.8,Inputs!$S$36+AA3))*$AH$3 -> 0.4653024 | AB38: =(1-MIN(0.8,Inputs!$T$36+AB3))*$AH$3 -> 0.4612208 | AC38: =(1-MIN(0.8,Inputs!$U$36+AC3))*$AH$3 -> 0.4571392 | AD38: =(1-MIN(0.8,Inputs!$V$36+AD3))*$AH$3 -> 0.4530576 | AE38: =(1-MIN(0.8,Inputs!$W$36+AE3))*$AH$3 -> 0.448976
A39: Grid battery storage | B39: BESS | C39: t LCE | D39: =D37*D38*1000 -> 10.204 | E39: =E37*E38*1000 -> 10.204 | F39: =F37*F38*1000 -> 10.204 | G39: =G37*G38*1000 -> 10.204 | H39: =H37*H38*1000 -> 10.204 | I39: =I37*I38*1000 -> 10.204 | J39: =J37*J38*1000 -> 10.204 | K39: =K37*K38*1000 -> 10.204 | ... AE39: =AE37*AE38*1000 -> 27208.278
A41: Smartphones (domestic sales) | B41: ELEC_Phone | C41: Units | D41: =Inputs!$H$38 -> 152000000 | E41: =Inputs!$H$38 -> 152000000 | F41: =Inputs!$H$38 -> 152000000 | G41: =Inputs!$H$38 -> 152000000 | H41: =Inputs!$H$38 -> 152000000 | I41: =Inputs!$H$38 -> 152000000 | J41: =Inputs!$H$38 -> 152000000 | K41: =Inputs!$H$38 -> 152000000 | ... P41: =Inputs!$H$38 -> 152000000 | Q41: =Inputs!$I$38 -> 1.5355071e+08 | R41: =Inputs!$J$38 -> 1.5510141e+08 | S41: =Inputs!$K$38 -> 1.5665212e+08 | T41: =Inputs!$L$38 -> 1.5820282e+08 | U41: =Inputs!$M$38 -> 1.5975353e+08 | V41: =Inputs!$N$38 -> 1.6138333e+08 | W41: =Inputs!$O$38 -> 1.6301314e+08 | X41: =Inputs!$P$38 -> 1.6464295e+08 | Y41: =Inputs!$Q$38 -> 1.6627276e+08 | Z41: =Inputs!$R$38 -> 1.6790256e+08 | AA41: =Inputs!$S$38 -> 1.6961551e+08 | AB41: =Inputs!$T$38 -> 1.7132845e+08 | AC41: =Inputs!$U$38 -> 1.7304139e+08 | AD41: =Inputs!$V$38 -> 1.7475434e+08 | AE41: =Inputs!$W$38 -> 1.7646728e+08
A42: Smartphones (domestic sales) | B42: ELEC_Phone | C42: GWh | D42: =D41*Inputs!$H$44/1000000000 -> 2.9488 | E42: =E41*Inputs!$H$44/1000000000 -> 2.9488 | F42: =F41*Inputs!$H$44/1000000000 -> 2.9488 | G42: =G41*Inputs!$H$44/1000000000 -> 2.9488 | H42: =H41*Inputs!$H$44/1000000000 -> 2.9488 | I42: =I41*Inputs!$H$44/1000000000 -> 2.9488 | J42: =J41*Inputs!$H$44/1000000000 -> 2.9488 | K42: =K41*Inputs!$H$44/1000000000 -> 2.9488 | ... P42: =P41*Inputs!$H$44/1000000000 -> 2.9488 | Q42: =Q41*Inputs!$I$44/1000000000 -> 3.0280199 | R42: =R41*Inputs!$J$44/1000000000 -> 3.1082323 | S42: =S41*Inputs!$K$44/1000000000 -> 3.1894371 | T42: =T41*Inputs!$L$44/1000000000 -> 3.2716344 | U42: =U41*Inputs!$M$44/1000000000 -> 3.3548241 | V42: =V41*Inputs!$N$44/1000000000 -> 3.4536034 | W42: =W41*Inputs!$O$44/1000000000 -> 3.5536865 | X42: =X41*Inputs!$P$44/1000000000 -> 3.6550735 | Y42: =Y41*Inputs!$Q$44/1000000000 -> 3.7577643 | Z42: =Z41*Inputs!$R$44/1000000000 -> 3.861759 | AA42: =AA41*Inputs!$S$44/1000000000 -> 3.9350798 | AB42: =AB41*Inputs!$T$44/1000000000 -> 4.0090857 | AC42: =AC41*Inputs!$U$44/1000000000 -> 4.0837769 | AD42: =AD41*Inputs!$V$44/1000000000 -> 4.1591532 | AE42: =AE41*Inputs!$W$44/1000000000 -> 4.2352147
A43: Smartphones (domestic sales) | B43: ELEC_Phone | C43: t LCE | D43: =D42*$AH$5*1000 -> 1943.2592 | E43: =E42*$AH$5*1000 -> 1943.2592 | F43: =F42*$AH$5*1000 -> 1943.2592 | G43: =G42*$AH$5*1000 -> 1943.2592 | H43: =H42*$AH$5*1000 -> 1943.2592 | I43: =I42*$AH$5*1000 -> 1943.2592 | J43: =J42*$AH$5*1000 -> 1943.2592 | K43: =K42*$AH$5*1000 -> 1943.2592 | ... AE43: =AE42*$AH$5*1000 -> 2791.0065
A44: Laptops and PCs | B44: ELEC_PC | C44: Units | D44: =Inputs!$H$39 -> 15900000 | E44: =Inputs!$H$39 -> 15900000 | F44: =Inputs!$H$39 -> 15900000 | G44: =Inputs!$H$39 -> 15900000 | H44: =Inputs!$H$39 -> 15900000 | I44: =Inputs!$H$39 -> 15900000 | J44: =Inputs!$H$39 -> 15900000 | K44: =Inputs!$H$39 -> 15900000 | ... P44: =Inputs!$H$39 -> 15900000 | Q44: =Inputs!$I$39 -> 16588956 | R44: =Inputs!$J$39 -> 17277912 | S44: =Inputs!$K$39 -> 17966869 | T44: =Inputs!$L$39 -> 18655825 | U44: =Inputs!$M$39 -> 19344781 | V44: =Inputs!$N$39 -> 20183002 | W44: =Inputs!$O$39 -> 21021222 | X44: =Inputs!$P$39 -> 21859443 | Y44: =Inputs!$Q$39 -> 22697664 | Z44: =Inputs!$R$39 -> 23535884 | AA44: =Inputs!$S$39 -> 24555708 | AB44: =Inputs!$T$39 -> 25575531 | AC44: =Inputs!$U$39 -> 26595355 | AD44: =Inputs!$V$39 -> 27615178 | AE44: =Inputs!$W$39 -> 28635002
A45: Laptops and PCs | B45: ELEC_PC | C45: GWh | D45: =D44*Inputs!$H$45/1000000000 -> 0.795 | E45: =E44*Inputs!$H$45/1000000000 -> 0.795 | F45: =F44*Inputs!$H$45/1000000000 -> 0.795 | G45: =G44*Inputs!$H$45/1000000000 -> 0.795 | H45: =H44*Inputs!$H$45/1000000000 -> 0.795 | I45: =I44*Inputs!$H$45/1000000000 -> 0.795 | J45: =J44*Inputs!$H$45/1000000000 -> 0.795 | K45: =K44*Inputs!$H$45/1000000000 -> 0.795 | ... P45: =P44*Inputs!$H$45/1000000000 -> 0.795 | Q45: =Q44*Inputs!$I$45/1000000000 -> 0.83608339 | R45: =R44*Inputs!$J$45/1000000000 -> 0.87771795 | S45: =S44*Inputs!$K$45/1000000000 -> 0.91990368 | T45: =T44*Inputs!$L$45/1000000000 -> 0.96264057 | U45: =U44*Inputs!$M$45/1000000000 -> 1.0059286 | V45: =V44*Inputs!$N$45/1000000000 -> 1.0616259 | W45: =W44*Inputs!$O$45/1000000000 -> 1.118329 | X45: =X44*Inputs!$P$45/1000000000 -> 1.176038 | Y45: =Y44*Inputs!$Q$45/1000000000 -> 1.2347529 | Z45: =Z44*Inputs!$R$45/1000000000 -> 1.2944736 | AA45: =AA44*Inputs!$S$45/1000000000 -> 1.3505639 | AB45: =AB44*Inputs!$T$45/1000000000 -> 1.4066542 | AC45: =AC44*Inputs!$U$45/1000000000 -> 1.4627445 | AD45: =AD44*Inputs!$V$45/1000000000 -> 1.5188348 | AE45: =AE44*Inputs!$W$45/1000000000 -> 1.5749251
A46: Laptops and PCs | B46: ELEC_PC | C46: t LCE | D46: =D45*$AH$4*1000 -> 465.234 | E46: =E45*$AH$4*1000 -> 465.234 | F46: =F45*$AH$4*1000 -> 465.234 | G46: =G45*$AH$4*1000 -> 465.234 | H46: =H45*$AH$4*1000 -> 465.234 | I46: =I45*$AH$4*1000 -> 465.234 | J46: =J45*$AH$4*1000 -> 465.234 | K46: =K45*$AH$4*1000 -> 465.234 | ... AE46: =AE45*$AH$4*1000 -> 921.64617
A47: Tablets | B47: ELEC_Tablet | C47: Units | D47: =Inputs!$H$40 -> 4500000 | E47: =Inputs!$H$40 -> 4500000 | F47: =Inputs!$H$40 -> 4500000 | G47: =Inputs!$H$40 -> 4500000 | H47: =Inputs!$H$40 -> 4500000 | I47: =Inputs!$H$40 -> 4500000 | J47: =Inputs!$H$40 -> 4500000 | K47: =Inputs!$H$40 -> 4500000 | ... P47: =Inputs!$H$40 -> 4500000 | Q47: =Inputs!$I$40 -> 4643346.7 | R47: =Inputs!$J$40 -> 4786693.3 | S47: =Inputs!$K$40 -> 4930040 | T47: =Inputs!$L$40 -> 5073386.7 | U47: =Inputs!$M$40 -> 5216733.3 | V47: =Inputs!$N$40 -> 5382911.4 | W47: =Inputs!$O$40 -> 5549089.5 | X47: =Inputs!$P$40 -> 5715267.6 | Y47: =Inputs!$Q$40 -> 5881445.6 | Z47: =Inputs!$R$40 -> 6047623.7 | AA47: =Inputs!$S$40 -> 6240269.6 | AB47: =Inputs!$T$40 -> 6432915.6 | AC47: =Inputs!$U$40 -> 6625561.5 | AD47: =Inputs!$V$40 -> 6818207.4 | AE47: =Inputs!$W$40 -> 7010853.4
A48: Tablets | B48: ELEC_Tablet | C48: GWh | D48: =D47*Inputs!$H$46/1000000000 -> 0.126 | E48: =E47*Inputs!$H$46/1000000000 -> 0.126 | F48: =F47*Inputs!$H$46/1000000000 -> 0.126 | G48: =G47*Inputs!$H$46/1000000000 -> 0.126 | H48: =H47*Inputs!$H$46/1000000000 -> 0.126 | I48: =I47*Inputs!$H$46/1000000000 -> 0.126 | J48: =J47*Inputs!$H$46/1000000000 -> 0.126 | K48: =K47*Inputs!$H$46/1000000000 -> 0.126 | ... P48: =P47*Inputs!$H$46/1000000000 -> 0.126 | Q48: =Q47*Inputs!$I$46/1000000000 -> 0.13187105 | R48: =R47*Inputs!$J$46/1000000000 -> 0.13785677 | S48: =S47*Inputs!$K$46/1000000000 -> 0.14395717 | T48: =T47*Inputs!$L$46/1000000000 -> 0.15017225 | U48: =U47*Inputs!$M$46/1000000000 -> 0.156502 | V48: =V47*Inputs!$N$46/1000000000 -> 0.16364051 | W48: =W47*Inputs!$O$46/1000000000 -> 0.17091196 | X48: =X47*Inputs!$P$46/1000000000 -> 0.17831635 | Y48: =Y47*Inputs!$Q$46/1000000000 -> 0.18585368 | Z48: =Z47*Inputs!$R$46/1000000000 -> 0.19352396 | AA48: =AA47*Inputs!$S$46/1000000000 -> 0.19968863 | AB48: =AB47*Inputs!$T$46/1000000000 -> 0.2058533 | AC48: =AC47*Inputs!$U$46/1000000000 -> 0.21201797 | AD48: =AD47*Inputs!$V$46/1000000000 -> 0.21818264 | AE48: =AE47*Inputs!$W$46/1000000000 -> 0.22434731
A49: Tablets | B49: ELEC_Tablet | C49: t LCE | D49: =D48*$AH$5*1000 -> 83.034 | E49: =E48*$AH$5*1000 -> 83.034 | F49: =F48*$AH$5*1000 -> 83.034 | G49: =G48*$AH$5*1000 -> 83.034 | H49: =H48*$AH$5*1000 -> 83.034 | I49: =I48*$AH$5*1000 -> 83.034 | J49: =J48*$AH$5*1000 -> 83.034 | K49: =K48*$AH$5*1000 -> 83.034 | ... AE49: =AE48*$AH$5*1000 -> 147.84488
A50: Wearables | B50: ELEC_Wearable | C50: Units | D50: =Inputs!$H$41 -> 114200000 | E50: =Inputs!$H$41 -> 114200000 | F50: =Inputs!$H$41 -> 114200000 | G50: =Inputs!$H$41 -> 114200000 | H50: =Inputs!$H$41 -> 114200000 | I50: =Inputs!$H$41 -> 114200000 | J50: =Inputs!$H$41 -> 114200000 | K50: =Inputs!$H$41 -> 114200000 | ... P50: =Inputs!$H$41 -> 114200000 | Q50: =Inputs!$I$41 -> 1.1536507e+08 | R50: =Inputs!$J$41 -> 1.1653014e+08 | S50: =Inputs!$K$41 -> 1.1769521e+08 | T50: =Inputs!$L$41 -> 1.1886028e+08 | U50: =Inputs!$M$41 -> 1.2002535e+08 | V50: =Inputs!$N$41 -> 1.2124985e+08 | W50: =Inputs!$O$41 -> 1.2247435e+08 | X50: =Inputs!$P$41 -> 1.2369885e+08 | Y50: =Inputs!$Q$41 -> 1.2492335e+08 | Z50: =Inputs!$R$41 -> 1.2614785e+08 | AA50: =Inputs!$S$41 -> 1.2743481e+08 | AB50: =Inputs!$T$41 -> 1.2872177e+08 | AC50: =Inputs!$U$41 -> 1.3000873e+08 | AD50: =Inputs!$V$41 -> 1.3129569e+08 | AE50: =Inputs!$W$41 -> 1.3258265e+08
A51: Wearables | B51: ELEC_Wearable | C51: GWh | D51: =D50*Inputs!$H$47/1000000000 -> 0.08565 | E51: =E50*Inputs!$H$47/1000000000 -> 0.08565 | F51: =F50*Inputs!$H$47/1000000000 -> 0.08565 | G51: =G50*Inputs!$H$47/1000000000 -> 0.08565 | H51: =H50*Inputs!$H$47/1000000000 -> 0.08565 | I51: =I50*Inputs!$H$47/1000000000 -> 0.08565 | J51: =J50*Inputs!$H$47/1000000000 -> 0.08565 | K51: =K50*Inputs!$H$47/1000000000 -> 0.08565 | ... P51: =P50*Inputs!$H$47/1000000000 -> 0.08565 | Q51: =Q50*Inputs!$I$47/1000000000 -> 0.087677453 | R51: =R50*Inputs!$J$47/1000000000 -> 0.089728207 | S51: =S50*Inputs!$K$47/1000000000 -> 0.091802263 | T51: =T50*Inputs!$L$47/1000000000 -> 0.09389962 | U51: =U50*Inputs!$M$47/1000000000 -> 0.096020278 | V51: =V50*Inputs!$N$47/1000000000 -> 0.099424875 | W51: =W50*Inputs!$O$47/1000000000 -> 0.10287845 | X51: =X50*Inputs!$P$47/1000000000 -> 0.10638101 | Y51: =Y50*Inputs!$Q$47/1000000000 -> 0.10993255 | Z51: =Z50*Inputs!$R$47/1000000000 -> 0.11353306 | AA51: =AA50*Inputs!$S$47/1000000000 -> 0.11469133 | AB51: =AB50*Inputs!$T$47/1000000000 -> 0.11584959 | AC51: =AC50*Inputs!$U$47/1000000000 -> 0.11700786 | AD51: =AD50*Inputs!$V$47/1000000000 -> 0.11816612 | AE51: =AE50*Inputs!$W$47/1000000000 -> 0.11932439
A52: Wearables | B52: ELEC_Wearable | C52: t LCE | D52: =D51*$AH$5*1000 -> 56.44335 | E52: =E51*$AH$5*1000 -> 56.44335 | F52: =F51*$AH$5*1000 -> 56.44335 | G52: =G51*$AH$5*1000 -> 56.44335 | H52: =H51*$AH$5*1000 -> 56.44335 | I52: =I51*$AH$5*1000 -> 56.44335 | J52: =J51*$AH$5*1000 -> 56.44335 | K52: =K51*$AH$5*1000 -> 56.44335 | ... AE52: =AE51*$AH$5*1000 -> 78.634773
A53: Power banks | B53: ELEC_PowerBank | C53: Units | D53: =Inputs!$H$42 -> 25000000 | E53: =Inputs!$H$42 -> 25000000 | F53: =Inputs!$H$42 -> 25000000 | G53: =Inputs!$H$42 -> 25000000 | H53: =Inputs!$H$42 -> 25000000 | I53: =Inputs!$H$42 -> 25000000 | J53: =Inputs!$H$42 -> 25000000 | K53: =Inputs!$H$42 -> 25000000 | ... P53: =Inputs!$H$42 -> 25000000 | Q53: =Inputs!$I$42 -> 25520404 | R53: =Inputs!$J$42 -> 26040808 | S53: =Inputs!$K$42 -> 26561212 | T53: =Inputs!$L$42 -> 27081616 | U53: =Inputs!$M$42 -> 27602020 | V53: =Inputs!$N$42 -> 28176588 | W53: =Inputs!$O$42 -> 28751156 | X53: =Inputs!$P$42 -> 29325724 | Y53: =Inputs!$Q$42 -> 29900292 | Z53: =Inputs!$R$42 -> 30474860 | AA53: =Inputs!$S$42 -> 31109230 | AB53: =Inputs!$T$42 -> 31743600 | AC53: =Inputs!$U$42 -> 32377969 | AD53: =Inputs!$V$42 -> 33012339 | AE53: =Inputs!$W$42 -> 33646708
A54: Power banks | B54: ELEC_PowerBank | C54: GWh | D54: =D53*Inputs!$H$48/1000000000 -> 0.925 | E54: =E53*Inputs!$H$48/1000000000 -> 0.925 | F54: =F53*Inputs!$H$48/1000000000 -> 0.925 | G54: =G53*Inputs!$H$48/1000000000 -> 0.925 | H54: =H53*Inputs!$H$48/1000000000 -> 0.925 | I54: =I53*Inputs!$H$48/1000000000 -> 0.925 | J54: =J53*Inputs!$H$48/1000000000 -> 0.925 | K54: =K53*Inputs!$H$48/1000000000 -> 0.925 | ... P54: =P53*Inputs!$H$48/1000000000 -> 0.925 | Q54: =Q53*Inputs!$I$48/1000000000 -> 0.95956719 | R54: =R53*Inputs!$J$48/1000000000 -> 0.99475887 | S54: =S53*Inputs!$K$48/1000000000 -> 1.030575 | T54: =T53*Inputs!$L$48/1000000000 -> 1.0670157 | U54: =U53*Inputs!$M$48/1000000000 -> 1.1040808 | V54: =V53*Inputs!$N$48/1000000000 -> 1.1270635 | W54: =W53*Inputs!$O$48/1000000000 -> 1.1500462 | X54: =X53*Inputs!$P$48/1000000000 -> 1.173029 | Y54: =Y53*Inputs!$Q$48/1000000000 -> 1.1960117 | Z54: =Z53*Inputs!$R$48/1000000000 -> 1.2189944 | AA54: =AA53*Inputs!$S$48/1000000000 -> 1.2443692 | AB54: =AB53*Inputs!$T$48/1000000000 -> 1.269744 | AC54: =AC53*Inputs!$U$48/1000000000 -> 1.2951188 | AD54: =AD53*Inputs!$V$48/1000000000 -> 1.3204936 | AE54: =AE53*Inputs!$W$48/1000000000 -> 1.3458683
A55: Power banks | B55: ELEC_PowerBank | C55: t LCE | D55: =D54*$AH$4*1000 -> 541.31 | E55: =E54*$AH$4*1000 -> 541.31 | F55: =F54*$AH$4*1000 -> 541.31 | G55: =G54*$AH$4*1000 -> 541.31 | H55: =H54*$AH$4*1000 -> 541.31 | I55: =I54*$AH$4*1000 -> 541.31 | J55: =J54*$AH$4*1000 -> 541.31 | K55: =K54*$AH$4*1000 -> 541.31 | ... AE55: =AE54*$AH$4*1000 -> 787.60215
A56: Phones assembled for export | B56: ELEC_ExportAssembly | C56: Units | D56: =Inputs!$H$43 -> 90000000 | E56: =Inputs!$H$43 -> 90000000 | F56: =Inputs!$H$43 -> 90000000 | G56: =Inputs!$H$43 -> 90000000 | H56: =Inputs!$H$43 -> 90000000 | I56: =Inputs!$H$43 -> 90000000 | J56: =Inputs!$H$43 -> 90000000 | K56: =Inputs!$H$43 -> 90000000 | ... P56: =Inputs!$H$43 -> 90000000 | Q56: =Inputs!$I$43 -> 97245931 | R56: =Inputs!$J$43 -> 1.0449186e+08 | S56: =Inputs!$K$43 -> 1.1173779e+08 | T56: =Inputs!$L$43 -> 1.1898372e+08 | U56: =Inputs!$M$43 -> 1.2622966e+08 | V56: =Inputs!$N$43 -> 1.3639245e+08 | W56: =Inputs!$O$43 -> 1.4655524e+08 | X56: =Inputs!$P$43 -> 1.5671804e+08 | Y56: =Inputs!$Q$43 -> 1.6688083e+08 | Z56: =Inputs!$R$43 -> 1.7704362e+08 | AA56: =Inputs!$S$43 -> 1.9129747e+08 | AB56: =Inputs!$T$43 -> 2.0555131e+08 | AC56: =Inputs!$U$43 -> 2.1980515e+08 | AD56: =Inputs!$V$43 -> 2.34059e+08 | AE56: =Inputs!$W$43 -> 2.4831284e+08
A57: Phones assembled for export | B57: ELEC_ExportAssembly | C57: GWh | D57: =D56*Inputs!$H$49/1000000000 -> 1.746 | E57: =E56*Inputs!$H$49/1000000000 -> 1.746 | F57: =F56*Inputs!$H$49/1000000000 -> 1.746 | G57: =G56*Inputs!$H$49/1000000000 -> 1.746 | H57: =H56*Inputs!$H$49/1000000000 -> 1.746 | I57: =I56*Inputs!$H$49/1000000000 -> 1.746 | J57: =J56*Inputs!$H$49/1000000000 -> 1.746 | K57: =K56*Inputs!$H$49/1000000000 -> 1.746 | ... P57: =P56*Inputs!$H$49/1000000000 -> 1.746 | Q57: =Q56*Inputs!$I$49/1000000000 -> 1.9176898 | R57: =R56*Inputs!$J$49/1000000000 -> 2.0940169 | S57: =S56*Inputs!$K$49/1000000000 -> 2.2749815 | T57: =T56*Inputs!$L$49/1000000000 -> 2.4605834 | U57: =U56*Inputs!$M$49/1000000000 -> 2.6508228 | V57: =V56*Inputs!$N$49/1000000000 -> 2.9187984 | W57: =W56*Inputs!$O$49/1000000000 -> 3.1949043 | X57: =X56*Inputs!$P$49/1000000000 -> 3.4791404 | Y57: =Y56*Inputs!$Q$49/1000000000 -> 3.7715067 | Z57: =Z56*Inputs!$R$49/1000000000 -> 4.0720033 | AA57: =AA56*Inputs!$S$49/1000000000 -> 4.4381012 | AB57: =AB56*Inputs!$T$49/1000000000 -> 4.8099006 | AC57: =AC56*Inputs!$U$49/1000000000 -> 5.1874016 | AD57: =AD56*Inputs!$V$49/1000000000 -> 5.5706041 | AE57: =AE56*Inputs!$W$49/1000000000 -> 5.9595081
A58: Phones assembled for export | B58: ELEC_ExportAssembly | C58: t LCE | D58: =D57*$AH$5*1000 -> 1150.614 | E58: =E57*$AH$5*1000 -> 1150.614 | F58: =F57*$AH$5*1000 -> 1150.614 | G58: =G57*$AH$5*1000 -> 1150.614 | H58: =H57*$AH$5*1000 -> 1150.614 | I58: =I57*$AH$5*1000 -> 1150.614 | J58: =J57*$AH$5*1000 -> 1150.614 | K58: =K57*$AH$5*1000 -> 1150.614 | ... AE58: =AE57*$AH$5*1000 -> 3927.3159
A60: Defence and aerospace | B60: DEF_Defence | C60: t LCE | P60: =Inputs!$H$50 -> 150 | Q60: =Inputs!$I$50 -> 164.07984 | R60: =Inputs!$J$50 -> 178.15968 | S60: =Inputs!$K$50 -> 192.23953 | T60: =Inputs!$L$50 -> 206.31937 | U60: =Inputs!$M$50 -> 220.39921 | V60: =Inputs!$N$50 -> 241.08712 | W60: =Inputs!$O$50 -> 261.77503 | X60: =Inputs!$P$50 -> 282.46293 | Y60: =Inputs!$Q$50 -> 303.15084 | Z60: =Inputs!$R$50 -> 323.83875 | AA60: =Inputs!$S$50 -> 354.23607 | AB60: =Inputs!$T$50 -> 384.6334 | AC60: =Inputs!$U$50 -> 415.03072 | AD60: =Inputs!$V$50 -> 445.42804 | AE60: =Inputs!$W$50 -> 475.82537
A61: Lubricating greases | B61: IND_Grease | C61: t LCE | P61: =Inputs!$H$51 -> 1080.5 | Q61: =Inputs!$I$51 -> 1140.2044 | R61: =Inputs!$J$51 -> 1199.9089 | S61: =Inputs!$K$51 -> 1259.6133 | T61: =Inputs!$L$51 -> 1319.3178 | U61: =Inputs!$M$51 -> 1379.0222 | V61: =Inputs!$N$51 -> 1455.2219 | W61: =Inputs!$O$51 -> 1531.4216 | X61: =Inputs!$P$51 -> 1607.6213 | Y61: =Inputs!$Q$51 -> 1683.821 | Z61: =Inputs!$R$51 -> 1760.0206 | AA61: =Inputs!$S$51 -> 1857.2729 | AB61: =Inputs!$T$51 -> 1954.5251 | AC61: =Inputs!$U$51 -> 2051.7774 | AD61: =Inputs!$V$51 -> 2149.0296 | AE61: =Inputs!$W$51 -> 2246.2819
A62: Glass and ceramics | B62: IND_GlassCeramics | C62: t LCE | P62: =Inputs!$H$52 -> 251.7 | Q62: =Inputs!$I$52 -> 265.60801 | R62: =Inputs!$J$52 -> 279.51603 | S62: =Inputs!$K$52 -> 293.42404 | T62: =Inputs!$L$52 -> 307.33206 | U62: =Inputs!$M$52 -> 321.24007 | V62: =Inputs!$N$52 -> 338.99061 | W62: =Inputs!$O$52 -> 356.74115 | X62: =Inputs!$P$52 -> 374.49169 | Y62: =Inputs!$Q$52 -> 392.24224 | Z62: =Inputs!$R$52 -> 409.99278 | AA62: =Inputs!$S$52 -> 432.64747 | AB62: =Inputs!$T$52 -> 455.30216 | AC62: =Inputs!$U$52 -> 477.95684 | AD62: =Inputs!$V$52 -> 500.61153 | AE62: =Inputs!$W$52 -> 523.26622
A63: Pharma, air treatment and other | B63: IND_Pharma_Other | C63: t LCE | P63: =Inputs!$H$53 -> 371.8 | Q63: =Inputs!$I$53 -> 392.3443 | R63: =Inputs!$J$53 -> 412.88859 | S63: =Inputs!$K$53 -> 433.43289 | T63: =Inputs!$L$53 -> 453.97719 | U63: =Inputs!$M$53 -> 474.52148 | V63: =Inputs!$N$53 -> 500.74179 | W63: =Inputs!$O$53 -> 526.9621 | X63: =Inputs!$P$53 -> 553.18241 | Y63: =Inputs!$Q$53 -> 579.40271 | Z63: =Inputs!$R$53 -> 605.62302 | AA63: =Inputs!$S$53 -> 639.08752 | AB63: =Inputs!$T$53 -> 672.55201 | AC63: =Inputs!$U$53 -> 706.01651 | AD63: =Inputs!$V$53 -> 739.481 | AE63: =Inputs!$W$53 -> 772.9455
A65: Totals | B65: Energy | C65: Energy transition demand (t LCE) | P65: =P8+P13+P18+P23+P28+P33+P39 -> 10106.527 | Q65: =Q8+Q13+Q18+Q23+Q28+Q33+Q39 -> 18184.509 | R65: =R8+R13+R18+R23+R28+R33+R39 -> 26846.741 | S65: =S8+S13+S18+S23+S28+S33+S39 -> 36116.708 | T65: =T8+T13+T18+T23+T28+T33+T39 -> 46017.285 | U65: =U8+U13+U18+U23+U28+U33+U39 -> 56570.732 | V65: =V8+V13+V18+V23+V28+V33+V39 -> 68096.011 | W65: =W8+W13+W18+W23+W28+W33+W39 -> 80791.249 | ... AE65: =AE8+AE13+AE18+AE23+AE28+AE33+AE39 -> 253009.24
A66: Totals | B66: NonEnergy | C66: Non-energy demand (t LCE) | P66: =P43+P46+P49+P52+P55+P58+P60+P61+P62+P63 -> 6093.8945 | Q66: =Q43+Q46+Q49+Q52+Q55+Q58+Q60+Q61+Q62+Q63 -> 6416.9565 | R66: =R43+R46+R49+R52+R55+R58+R60+R61+R62+R63 -> 6744.5074 | S66: =S43+S46+S49+S52+S55+S58+S60+S61+S62+S63 -> 7076.5472 | T66: =T43+T46+T49+T52+T55+T58+T60+T61+T62+T63 -> 7413.0761 | U66: =U43+U46+U49+U52+U55+U58+U60+U61+U62+U63 -> 7754.094 | V66: =V43+V46+V49+V52+V55+V58+V60+V61+V62+V63 -> 8189.6353 | W66: =W43+W46+W49+W52+W55+W58+W60+W61+W62+W63 -> 8632.1023 | ... AE66: =AE43+AE46+AE49+AE52+AE55+AE58+AE60+AE61+AE62+AE63 -> 12672.369
A67: Totals | B67: All | C67: Total demand (t LCE) | P67: =P65+P66 -> 16200.421 | Q67: =Q65+Q66 -> 24601.465 | R67: =R65+R66 -> 33591.248 | S67: =S65+S66 -> 43193.256 | T67: =T65+T66 -> 53430.361 | U67: =U65+U66 -> 64324.826 | V67: =V65+V66 -> 76285.647 | W67: =W65+W66 -> 89423.351 | ... AE67: =AE65+AE66 -> 265681.61
A68: Totals | B68: Battery | C68: Battery demand incl. electronics (t LCE) | P68: =P65+P43+P46+P49+P52+P55+P58 -> 14346.421 | Q68: =Q65+Q43+Q46+Q49+Q52+Q55+Q58 -> 22639.229 | R68: =R65+R43+R46+R49+R52+R55+R58 -> 31520.775 | S68: =S65+S43+S46+S49+S52+S55+S58 -> 41014.546 | T68: =T65+T43+T46+T49+T52+T55+T58 -> 51143.414 | U68: =U65+U43+U46+U49+U52+U55+U58 -> 61929.643 | V68: =V65+V43+V46+V49+V52+V55+V58 -> 73749.605 | W68: =W65+W43+W46+W49+W52+W55+W58 -> 86746.451 | ... AE68: =AE65+AE43+AE46+AE49+AE52+AE55+AE58 -> 261663.29
A70: Supply | B70: Recycling | C70: Collection rate EV and storage | P70: =IF(Control!$B$5,MAX(Inputs!$H$58,IF(2025<=2030,Inputs!$H$58+(0.9-Inputs!$H$58)*(2025-2025)/5,0.9)),Inputs!$H$58) -> 0.3 | Q70: =IF(Control!$B$5,MAX(Inputs!$I$58,IF(2026<=2030,Inputs!$H$58+(0.9-Inputs!$H$58)*(2026-2025)/5,0.9)),Inputs!$I$58) -> 0.38 | R70: =IF(Control!$B$5,MAX(Inputs!$J$58,IF(2027<=2030,Inputs!$H$58+(0.9-Inputs!$H$58)*(2027-2025)/5,0.9)),Inputs!$J$58) -> 0.46 | S70: =IF(Control!$B$5,MAX(Inputs!$K$58,IF(2028<=2030,Inputs!$H$58+(0.9-Inputs!$H$58)*(2028-2025)/5,0.9)),Inputs!$K$58) -> 0.54 | T70: =IF(Control!$B$5,MAX(Inputs!$L$58,IF(2029<=2030,Inputs!$H$58+(0.9-Inputs!$H$58)*(2029-2025)/5,0.9)),Inputs!$L$58) -> 0.62 | U70: =IF(Control!$B$5,MAX(Inputs!$M$58,IF(2030<=2030,Inputs!$H$58+(0.9-Inputs!$H$58)*(2030-2025)/5,0.9)),Inputs!$M$58) -> 0.7 | V70: =IF(Control!$B$5,MAX(Inputs!$N$58,IF(2031<=2030,Inputs!$H$58+(0.9-Inputs!$H$58)*(2031-2025)/5,0.9)),Inputs!$N$58) -> 0.73 | W70: =IF(Control!$B$5,MAX(Inputs!$O$58,IF(2032<=2030,Inputs!$H$58+(0.9-Inputs!$H$58)*(2032-2025)/5,0.9)),Inputs!$O$58) -> 0.76 | X70: =IF(Control!$B$5,MAX(Inputs!$P$58,IF(2033<=2030,Inputs!$H$58+(0.9-Inputs!$H$58)*(2033-2025)/5,0.9)),Inputs!$P$58) -> 0.79 | Y70: =IF(Control!$B$5,MAX(Inputs!$Q$58,IF(2034<=2030,Inputs!$H$58+(0.9-Inputs!$H$58)*(2034-2025)/5,0.9)),Inputs!$Q$58) -> 0.82 | Z70: =IF(Control!$B$5,MAX(Inputs!$R$58,IF(2035<=2030,Inputs!$H$58+(0.9-Inputs!$H$58)*(2035-2025)/5,0.9)),Inputs!$R$58) -> 0.85 | AA70: =IF(Control!$B$5,MAX(Inputs!$S$58,IF(2036<=2030,Inputs!$H$58+(0.9-Inputs!$H$58)*(2036-2025)/5,0.9)),Inputs!$S$58) -> 0.86 | AB70: =IF(Control!$B$5,MAX(Inputs!$T$58,IF(2037<=2030,Inputs!$H$58+(0.9-Inputs!$H$58)*(2037-2025)/5,0.9)),Inputs!$T$58) -> 0.87 | AC70: =IF(Control!$B$5,MAX(Inputs!$U$58,IF(2038<=2030,Inputs!$H$58+(0.9-Inputs!$H$58)*(2038-2025)/5,0.9)),Inputs!$U$58) -> 0.88 | AD70: =IF(Control!$B$5,MAX(Inputs!$V$58,IF(2039<=2030,Inputs!$H$58+(0.9-Inputs!$H$58)*(2039-2025)/5,0.9)),Inputs!$V$58) -> 0.89 | AE70: =IF(Control!$B$5,MAX(Inputs!$W$58,IF(2040<=2030,Inputs!$H$58+(0.9-Inputs!$H$58)*(2040-2025)/5,0.9)),Inputs!$W$58) -> 0.9
A71: Supply | B71: Recycling | C71: Collection rate electronics | P71: =IF(Control!$B$5,MAX(Inputs!$H$59,IF(2025<=2030,Inputs!$H$59+(0.7-Inputs!$H$59)*(2025-2025)/5,0.7)),Inputs!$H$59) -> 0.15 | Q71: =IF(Control!$B$5,MAX(Inputs!$I$59,IF(2026<=2030,Inputs!$H$59+(0.7-Inputs!$H$59)*(2026-2025)/5,0.7)),Inputs!$I$59) -> 0.19 | R71: =IF(Control!$B$5,MAX(Inputs!$J$59,IF(2027<=2030,Inputs!$H$59+(0.7-Inputs!$H$59)*(2027-2025)/5,0.7)),Inputs!$J$59) -> 0.23 | S71: =IF(Control!$B$5,MAX(Inputs!$K$59,IF(2028<=2030,Inputs!$H$59+(0.7-Inputs!$H$59)*(2028-2025)/5,0.7)),Inputs!$K$59) -> 0.27 | T71: =IF(Control!$B$5,MAX(Inputs!$L$59,IF(2029<=2030,Inputs!$H$59+(0.7-Inputs!$H$59)*(2029-2025)/5,0.7)),Inputs!$L$59) -> 0.31 | U71: =IF(Control!$B$5,MAX(Inputs!$M$59,IF(2030<=2030,Inputs!$H$59+(0.7-Inputs!$H$59)*(2030-2025)/5,0.7)),Inputs!$M$59) -> 0.35 | V71: =IF(Control!$B$5,MAX(Inputs!$N$59,IF(2031<=2030,Inputs!$H$59+(0.7-Inputs!$H$59)*(2031-2025)/5,0.7)),Inputs!$N$59) -> 0.39 | W71: =IF(Control!$B$5,MAX(Inputs!$O$59,IF(2032<=2030,Inputs!$H$59+(0.7-Inputs!$H$59)*(2032-2025)/5,0.7)),Inputs!$O$59) -> 0.43 | X71: =IF(Control!$B$5,MAX(Inputs!$P$59,IF(2033<=2030,Inputs!$H$59+(0.7-Inputs!$H$59)*(2033-2025)/5,0.7)),Inputs!$P$59) -> 0.47 | Y71: =IF(Control!$B$5,MAX(Inputs!$Q$59,IF(2034<=2030,Inputs!$H$59+(0.7-Inputs!$H$59)*(2034-2025)/5,0.7)),Inputs!$Q$59) -> 0.51 | Z71: =IF(Control!$B$5,MAX(Inputs!$R$59,IF(2035<=2030,Inputs!$H$59+(0.7-Inputs!$H$59)*(2035-2025)/5,0.7)),Inputs!$R$59) -> 0.55 | AA71: =IF(Control!$B$5,MAX(Inputs!$S$59,IF(2036<=2030,Inputs!$H$59+(0.7-Inputs!$H$59)*(2036-2025)/5,0.7)),Inputs!$S$59) -> 0.58 | AB71: =IF(Control!$B$5,MAX(Inputs!$T$59,IF(2037<=2030,Inputs!$H$59+(0.7-Inputs!$H$59)*(2037-2025)/5,0.7)),Inputs!$T$59) -> 0.61 | AC71: =IF(Control!$B$5,MAX(Inputs!$U$59,IF(2038<=2030,Inputs!$H$59+(0.7-Inputs!$H$59)*(2038-2025)/5,0.7)),Inputs!$U$59) -> 0.64 | AD71: =IF(Control!$B$5,MAX(Inputs!$V$59,IF(2039<=2030,Inputs!$H$59+(0.7-Inputs!$H$59)*(2039-2025)/5,0.7)),Inputs!$V$59) -> 0.67 | AE71: =IF(Control!$B$5,MAX(Inputs!$W$59,IF(2040<=2030,Inputs!$H$59+(0.7-Inputs!$H$59)*(2040-2025)/5,0.7)),Inputs!$W$59) -> 0.7
A72: Supply | B72: Recycling | C72: Lithium recovery | P72: =IF(Control!$B$5,MAX(Inputs!$H$60,IF(2025<=2030,Inputs!$H$60+(0.95-Inputs!$H$60)*(2025-2025)/5,0.95)),Inputs!$H$60) -> 0.8 | Q72: =IF(Control!$B$5,MAX(Inputs!$I$60,IF(2026<=2030,Inputs!$H$60+(0.95-Inputs!$H$60)*(2026-2025)/5,0.95)),Inputs!$I$60) -> 0.82 | R72: =IF(Control!$B$5,MAX(Inputs!$J$60,IF(2027<=2030,Inputs!$H$60+(0.95-Inputs!$H$60)*(2027-2025)/5,0.95)),Inputs!$J$60) -> 0.84 | S72: =IF(Control!$B$5,MAX(Inputs!$K$60,IF(2028<=2030,Inputs!$H$60+(0.95-Inputs!$H$60)*(2028-2025)/5,0.95)),Inputs!$K$60) -> 0.86 | T72: =IF(Control!$B$5,MAX(Inputs!$L$60,IF(2029<=2030,Inputs!$H$60+(0.95-Inputs!$H$60)*(2029-2025)/5,0.95)),Inputs!$L$60) -> 0.88 | U72: =IF(Control!$B$5,MAX(Inputs!$M$60,IF(2030<=2030,Inputs!$H$60+(0.95-Inputs!$H$60)*(2030-2025)/5,0.95)),Inputs!$M$60) -> 0.9 | V72: =IF(Control!$B$5,MAX(Inputs!$N$60,IF(2031<=2030,Inputs!$H$60+(0.95-Inputs!$H$60)*(2031-2025)/5,0.95)),Inputs!$N$60) -> 0.904 | W72: =IF(Control!$B$5,MAX(Inputs!$O$60,IF(2032<=2030,Inputs!$H$60+(0.95-Inputs!$H$60)*(2032-2025)/5,0.95)),Inputs!$O$60) -> 0.908 | X72: =IF(Control!$B$5,MAX(Inputs!$P$60,IF(2033<=2030,Inputs!$H$60+(0.95-Inputs!$H$60)*(2033-2025)/5,0.95)),Inputs!$P$60) -> 0.912 | Y72: =IF(Control!$B$5,MAX(Inputs!$Q$60,IF(2034<=2030,Inputs!$H$60+(0.95-Inputs!$H$60)*(2034-2025)/5,0.95)),Inputs!$Q$60) -> 0.916 | Z72: =IF(Control!$B$5,MAX(Inputs!$R$60,IF(2035<=2030,Inputs!$H$60+(0.95-Inputs!$H$60)*(2035-2025)/5,0.95)),Inputs!$R$60) -> 0.92 | AA72: =IF(Control!$B$5,MAX(Inputs!$S$60,IF(2036<=2030,Inputs!$H$60+(0.95-Inputs!$H$60)*(2036-2025)/5,0.95)),Inputs!$S$60) -> 0.92 | AB72: =IF(Control!$B$5,MAX(Inputs!$T$60,IF(2037<=2030,Inputs!$H$60+(0.95-Inputs!$H$60)*(2037-2025)/5,0.95)),Inputs!$T$60) -> 0.92 | AC72: =IF(Control!$B$5,MAX(Inputs!$U$60,IF(2038<=2030,Inputs!$H$60+(0.95-Inputs!$H$60)*(2038-2025)/5,0.95)),Inputs!$U$60) -> 0.92 | AD72: =IF(Control!$B$5,MAX(Inputs!$V$60,IF(2039<=2030,Inputs!$H$60+(0.95-Inputs!$H$60)*(2039-2025)/5,0.95)),Inputs!$V$60) -> 0.92 | AE72: =IF(Control!$B$5,MAX(Inputs!$W$60,IF(2040<=2030,Inputs!$H$60+(0.95-Inputs!$H$60)*(2040-2025)/5,0.95)),Inputs!$W$60) -> 0.92
A73: Supply | B73: Recycling | C73: Recycled lithium (t LCE) | P73: =(J8*P70+J13*P70+M18*P70+F23*P70+H28*P70+H33*P70+D39*P70+M43*P71+K46*P71+L49*P71+N52*P71+M55*P71)*P72 -> 433.088 | Q73: =(K8*Q70+K13*Q70+N18*Q70+G23*Q70+I28*Q70+I33*Q70+E39*Q70+N43*Q71+L46*Q71+M49*Q71+O52*Q71+N55*Q71)*Q72 -> 582.80352 | R73: =(L8*R70+L13*R70+O18*R70+H23*R70+J28*R70+J33*R70+F39*R70+O43*R71+M46*R71+N49*R71+P52*R71+O55*R71)*R72 -> 840.78888 | S73: =(M8*S70+M13*S70+P18*S70+I23*S70+K28*S70+K33*S70+G39*S70+P43*S71+N46*S71+O49*S71+Q52*S71+P55*S71)*S72 -> 1391.5895 | T73: =(N8*T70+N13*T70+Q18*T70+J23*T70+L28*T70+L33*T70+H39*T70+Q43*T71+O46*T71+P49*T71+R52*T71+Q55*T71)*T72 -> 2025.1009 | U73: =(O8*U70+O13*U70+R18*U70+K23*U70+M28*U70+M33*U70+I39*U70+R43*U71+P46*U71+Q49*U71+S52*U71+R55*U71)*U72 -> 2987.4018 | V73: =(P8*V70+P13*V70+S18*V70+L23*V70+N28*V70+N33*V70+J39*V70+S43*V71+Q46*V71+R49*V71+T52*V71+S55*V71)*V72 -> 4378.5126 | W73: =(Q8*W70+Q13*W70+T18*W70+M23*W70+O28*W70+O33*W70+K39*W70+T43*W71+R46*W71+S49*W71+U52*W71+T55*W71)*W72 -> 6498.4752 | ... AE73: =(Y8*AE70+Y13*AE70+AB18*AE70+U23*AE70+W28*AE70+W33*AE70+S39*AE70+AB43*AE71+Z46*AE71+AA49*AE71+AC52*AE71+AB55*AE71)*AE72 -> 61140.278
A74: Supply | B74: Mining | C74: Domestic mining (t LCE) | P74: =MAX(IF(2025>=Inputs!$H$55,Inputs!$H$54,0),IF(Control!$B$8,IF(2025<2032,0,IF(2025<=2035,1500*(2025-2031)/4,1500+2500*(2025-2035)/5)),0)) -> 0 | Q74: =MAX(IF(2026>=Inputs!$I$55,Inputs!$I$54,0),IF(Control!$B$8,IF(2026<2032,0,IF(2026<=2035,1500*(2026-2031)/4,1500+2500*(2026-2035)/5)),0)) -> 0 | R74: =MAX(IF(2027>=Inputs!$J$55,Inputs!$J$54,0),IF(Control!$B$8,IF(2027<2032,0,IF(2027<=2035,1500*(2027-2031)/4,1500+2500*(2027-2035)/5)),0)) -> 0 | S74: =MAX(IF(2028>=Inputs!$K$55,Inputs!$K$54,0),IF(Control!$B$8,IF(2028<2032,0,IF(2028<=2035,1500*(2028-2031)/4,1500+2500*(2028-2035)/5)),0)) -> 0 | T74: =MAX(IF(2029>=Inputs!$L$55,Inputs!$L$54,0),IF(Control!$B$8,IF(2029<2032,0,IF(2029<=2035,1500*(2029-2031)/4,1500+2500*(2029-2035)/5)),0)) -> 0 | U74: =MAX(IF(2030>=Inputs!$M$55,Inputs!$M$54,0),IF(Control!$B$8,IF(2030<2032,0,IF(2030<=2035,1500*(2030-2031)/4,1500+2500*(2030-2035)/5)),0)) -> 0 | V74: =MAX(IF(2031>=Inputs!$N$55,Inputs!$N$54,0),IF(Control!$B$8,IF(2031<2032,0,IF(2031<=2035,1500*(2031-2031)/4,1500+2500*(2031-2035)/5)),0)) -> 0 | W74: =MAX(IF(2032>=Inputs!$O$55,Inputs!$O$54,0),IF(Control!$B$8,IF(2032<2032,0,IF(2032<=2035,1500*(2032-2031)/4,1500+2500*(2032-2035)/5)),0)) -> 0 | X74: =MAX(IF(2033>=Inputs!$P$55,Inputs!$P$54,0),IF(Control!$B$8,IF(2033<2032,0,IF(2033<=2035,1500*(2033-2031)/4,1500+2500*(2033-2035)/5)),0)) -> 0 | Y74: =MAX(IF(2034>=Inputs!$Q$55,Inputs!$Q$54,0),IF(Control!$B$8,IF(2034<2032,0,IF(2034<=2035,1500*(2034-2031)/4,1500+2500*(2034-2035)/5)),0)) -> 0 | Z74: =MAX(IF(2035>=Inputs!$R$55,Inputs!$R$54,0),IF(Control!$B$8,IF(2035<2032,0,IF(2035<=2035,1500*(2035-2031)/4,1500+2500*(2035-2035)/5)),0)) -> 0 | AA74: =MAX(IF(2036>=Inputs!$S$55,Inputs!$S$54,0),IF(Control!$B$8,IF(2036<2032,0,IF(2036<=2035,1500*(2036-2031)/4,1500+2500*(2036-2035)/5)),0)) -> 0 | AB74: =MAX(IF(2037>=Inputs!$T$55,Inputs!$T$54,0),IF(Control!$B$8,IF(2037<2032,0,IF(2037<=2035,1500*(2037-2031)/4,1500+2500*(2037-2035)/5)),0)) -> 0 | AC74: =MAX(IF(2038>=Inputs!$U$55,Inputs!$U$54,0),IF(Control!$B$8,IF(2038<2032,0,IF(2038<=2035,1500*(2038-2031)/4,1500+2500*(2038-2035)/5)),0)) -> 0 | AD74: =MAX(IF(2039>=Inputs!$V$55,Inputs!$V$54,0),IF(Control!$B$8,IF(2039<2032,0,IF(2039<=2035,1500*(2039-2031)/4,1500+2500*(2039-2035)/5)),0)) -> 480 | AE74: =MAX(IF(2040>=Inputs!$W$55,Inputs!$W$54,0),IF(Control!$B$8,IF(2040<2032,0,IF(2040<=2035,1500*(2040-2031)/4,1500+2500*(2040-2035)/5)),0)) -> 600
A75: Supply | B75: Equity | C75: Overseas equity (t LCE) | P75: =IF(2025>=Inputs!$H$57,Inputs!$H$56,0)+IF(AND(Control!$B$6,2025>=2031),IF(2025<=2035,10000+20000*(2025-2030)/5,30000+20000*(2025-2035)/5),0) -> 0 | Q75: =IF(2026>=Inputs!$I$57,Inputs!$I$56,0)+IF(AND(Control!$B$6,2026>=2031),IF(2026<=2035,10000+20000*(2026-2030)/5,30000+20000*(2026-2035)/5),0) -> 0 | R75: =IF(2027>=Inputs!$J$57,Inputs!$J$56,0)+IF(AND(Control!$B$6,2027>=2031),IF(2027<=2035,10000+20000*(2027-2030)/5,30000+20000*(2027-2035)/5),0) -> 0 | S75: =IF(2028>=Inputs!$K$57,Inputs!$K$56,0)+IF(AND(Control!$B$6,2028>=2031),IF(2028<=2035,10000+20000*(2028-2030)/5,30000+20000*(2028-2035)/5),0) -> 0 | T75: =IF(2029>=Inputs!$L$57,Inputs!$L$56,0)+IF(AND(Control!$B$6,2029>=2031),IF(2029<=2035,10000+20000*(2029-2030)/5,30000+20000*(2029-2035)/5),0) -> 0 | U75: =IF(2030>=Inputs!$M$57,Inputs!$M$56,0)+IF(AND(Control!$B$6,2030>=2031),IF(2030<=2035,10000+20000*(2030-2030)/5,30000+20000*(2030-2035)/5),0) -> 0 | V75: =IF(2031>=Inputs!$N$57,Inputs!$N$56,0)+IF(AND(Control!$B$6,2031>=2031),IF(2031<=2035,10000+20000*(2031-2030)/5,30000+20000*(2031-2035)/5),0) -> 0 | W75: =IF(2032>=Inputs!$O$57,Inputs!$O$56,0)+IF(AND(Control!$B$6,2032>=2031),IF(2032<=2035,10000+20000*(2032-2030)/5,30000+20000*(2032-2035)/5),0) -> 2400 | X75: =IF(2033>=Inputs!$P$57,Inputs!$P$56,0)+IF(AND(Control!$B$6,2033>=2031),IF(2033<=2035,10000+20000*(2033-2030)/5,30000+20000*(2033-2035)/5),0) -> 3600 | Y75: =IF(2034>=Inputs!$Q$57,Inputs!$Q$56,0)+IF(AND(Control!$B$6,2034>=2031),IF(2034<=2035,10000+20000*(2034-2030)/5,30000+20000*(2034-2035)/5),0) -> 4800 | Z75: =IF(2035>=Inputs!$R$57,Inputs!$R$56,0)+IF(AND(Control!$B$6,2035>=2031),IF(2035<=2035,10000+20000*(2035-2030)/5,30000+20000*(2035-2035)/5),0) -> 6000 | AA75: =IF(2036>=Inputs!$S$57,Inputs!$S$56,0)+IF(AND(Control!$B$6,2036>=2031),IF(2036<=2035,10000+20000*(2036-2030)/5,30000+20000*(2036-2035)/5),0) -> 7200 | AB75: =IF(2037>=Inputs!$T$57,Inputs!$T$56,0)+IF(AND(Control!$B$6,2037>=2031),IF(2037<=2035,10000+20000*(2037-2030)/5,30000+20000*(2037-2035)/5),0) -> 8400 | AC75: =IF(2038>=Inputs!$U$57,Inputs!$U$56,0)+IF(AND(Control!$B$6,2038>=2031),IF(2038<=2035,10000+20000*(2038-2030)/5,30000+20000*(2038-2035)/5),0) -> 9600 | AD75: =IF(2039>=Inputs!$V$57,Inputs!$V$56,0)+IF(AND(Control!$B$6,2039>=2031),IF(2039<=2035,10000+20000*(2039-2030)/5,30000+20000*(2039-2035)/5),0) -> 10800 | AE75: =IF(2040>=Inputs!$W$57,Inputs!$W$56,0)+IF(AND(Control!$B$6,2040>=2031),IF(2040<=2035,10000+20000*(2040-2030)/5,30000+20000*(2040-2035)/5),0) -> 12000
A76: Supply | B76: Ceiling | C76: Import ceiling (t LCE) | P76: =Inputs!$H$61*Control!$B$10 -> 46320 | Q76: =Inputs!$I$61*Control!$B$10 -> 52656 | R76: =Inputs!$J$61*Control!$B$10 -> 58992 | S76: =Inputs!$K$61*Control!$B$10 -> 65328 | T76: =Inputs!$L$61*Control!$B$10 -> 71664 | U76: =Inputs!$M$61*Control!$B$10 -> 78000 | V76: =Inputs!$N$61*Control!$B$10 -> 82800 | W76: =Inputs!$O$61*Control!$B$10 -> 87600 | X76: =Inputs!$P$61*Control!$B$10 -> 92400 | Y76: =Inputs!$Q$61*Control!$B$10 -> 97200 | Z76: =Inputs!$R$61*Control!$B$10 -> 102000 | AA76: =Inputs!$S$61*Control!$B$10 -> 107400 | AB76: =Inputs!$T$61*Control!$B$10 -> 112800 | AC76: =Inputs!$U$61*Control!$B$10 -> 118200 | AD76: =Inputs!$V$61*Control!$B$10 -> 123600 | AE76: =Inputs!$W$61*Control!$B$10 -> 129000
A78: Balance | B78: Bal | C78: Net import need (t LCE) | P78: =MAX(0,P67-P73-P74) -> 15767.333 | Q78: =MAX(0,Q67-Q73-Q74) -> 24018.662 | R78: =MAX(0,R67-R73-R74) -> 32750.459 | S78: =MAX(0,S67-S73-S74) -> 41801.666 | T78: =MAX(0,T67-T73-T74) -> 51405.26 | U78: =MAX(0,U67-U73-U74) -> 61337.425 | V78: =MAX(0,V67-V73-V74) -> 71907.134 | W78: =MAX(0,W67-W73-W74) -> 82924.876 | ... AE78: =MAX(0,AE67-AE73-AE74) -> 203941.34
A79: Balance | B79: Bal | C79: Open-market import need (t LCE) | P79: =MAX(0,P78-P75) -> 15767.333 | Q79: =MAX(0,Q78-Q75) -> 24018.662 | R79: =MAX(0,R78-R75) -> 32750.459 | S79: =MAX(0,S78-S75) -> 41801.666 | T79: =MAX(0,T78-T75) -> 51405.26 | U79: =MAX(0,U78-U75) -> 61337.425 | V79: =MAX(0,V78-V75) -> 71907.134 | W79: =MAX(0,W78-W75) -> 80524.876 | ... AE79: =MAX(0,AE78-AE75) -> 191941.34
A80: Balance | B80: Bal | C80: Available supply (t LCE) | P80: =P73+P74+P75+P76 -> 46753.088 | Q80: =Q73+Q74+Q75+Q76 -> 53238.804 | R80: =R73+R74+R75+R76 -> 59832.789 | S80: =S73+S74+S75+S76 -> 66719.589 | T80: =T73+T74+T75+T76 -> 73689.101 | U80: =U73+U74+U75+U76 -> 80987.402 | V80: =V73+V74+V75+V76 -> 87178.513 | W80: =W73+W74+W75+W76 -> 96498.475 | ... AE80: =AE73+AE74+AE75+AE76 -> 202740.28
A81: Balance | B81: Bal | C81: Shortfall (t LCE) | P81: =MAX(0,P67-P80) -> 0 | Q81: =MAX(0,Q67-Q80) -> 0 | R81: =MAX(0,R67-R80) -> 0 | S81: =MAX(0,S67-S80) -> 0 | T81: =MAX(0,T67-T80) -> 0 | U81: =MAX(0,U67-U80) -> 0 | V81: =MAX(0,V67-V80) -> 0 | W81: =MAX(0,W67-W80) -> 0 | ... AE81: =MAX(0,AE67-AE80) -> 62941.335
A82: Balance | B82: Bal | C82: Energy coverage ratio | P82: =MIN(1,MAX(0,P80-P66)/P65) -> 1 | Q82: =MIN(1,MAX(0,Q80-Q66)/Q65) -> 1 | R82: =MIN(1,MAX(0,R80-R66)/R65) -> 1 | S82: =MIN(1,MAX(0,S80-S66)/S65) -> 1 | T82: =MIN(1,MAX(0,T80-T66)/T65) -> 1 | U82: =MIN(1,MAX(0,U80-U66)/U65) -> 1 | V82: =MIN(1,MAX(0,V80-V66)/V65) -> 1 | W82: =MIN(1,MAX(0,W80-W66)/W65) -> 1 | ... AE82: =MIN(1,MAX(0,AE80-AE66)/AE65) -> 0.75122911
A83: Balance | B83: Bal | C83: Import dependence | P83: =P78/P67 -> 0.97326687 | Q83: =Q78/Q67 -> 0.97631021 | R83: =R78/R67 -> 0.97497 | S83: =S78/S67 -> 0.96778225 | T83: =T78/T67 -> 0.96209831 | U83: =U78/U67 -> 0.95355756 | V83: =V78/V67 -> 0.94260372 | W83: =W78/W67 -> 0.9273291 | ... AE83: =AE78/AE67 -> 0.76761554
A84: Balance | B84: Bal | C84: Recycled content share | P84: =P73/P68 -> 0.030187877 | Q84: =Q73/Q68 -> 0.025743082 | R84: =R73/R68 -> 0.026674118 | S84: =S73/S68 -> 0.03392917 | T84: =T73/T68 -> 0.039596513 | U84: =U73/U68 -> 0.048238641 | V84: =V73/V68 -> 0.05936998 | W84: =W73/W68 -> 0.074913442 | ... AE84: =AE73/AE68 -> 0.23366012
A85: Balance | B85: Bal | C85: Recycled content mandate (BWMR) | P85: 0 | Q85: 0 | R85: 0.05 | S85: 0.1 | T85: 0.15 | U85: 0.2 | V85: 0.2 | W85: 0.2 | X85: 0.2 | Y85: 0.2 | Z85: 0.2 | AA85: 0.2 | AB85: 0.2 | AC85: 0.2 | AD85: 0.2 | AE85: 0.2
